[{"passport_label": "12.10-2.0.2-2-2-2-2-5-10.1", "gen_vectors": [[6, 7, 8, 9, 10, 1, 2, 3, 4, 5], [6, 7, 8, 9, 10, 1, 2, 3, 4, 5], [6, 7, 8, 9, 10, 1, 2, 3, 4, 5], [6, 7, 8, 9, 10, 1, 2, 3, 4, 5], [6, 7, 8, 9, 10, 1, 2, 3, 4, 5], [2, 3, 4, 5, 1, 7, 8, 9, 10, 6], [10, 6, 7, 8, 9, 5, 1, 2, 3, 4]], "total_label": "12.10-2.0.2-2-2-2-2-5-10.1.1", "cc": [1, 1], "signature": "[0,2,2,2,2,2,5,10]", "label": "12.10-2.0.2-2-2-2-2-5-10", "genus": 12, "group": "[10,2]", "_id": {"$oid": "59515cbc3fce4a6697d4dc9c"}}, {"passport_label": "12.10-2.0.2-2-2-2-2-5-10.2", "gen_vectors": [[6, 7, 8, 9, 10, 1, 2, 3, 4, 5], [6, 7, 8, 9, 10, 1, 2, 3, 4, 5], [6, 7, 8, 9, 10, 1, 2, 3, 4, 5], [6, 7, 8, 9, 10, 1, 2, 3, 4, 5], [6, 7, 8, 9, 10, 1, 2, 3, 4, 5], [3, 4, 5, 1, 2, 8, 9, 10, 6, 7], [9, 10, 6, 7, 8, 4, 5, 1, 2, 3]], "total_label": "12.10-2.0.2-2-2-2-2-5-10.2.1", "cc": [2, 1], "signature": "[0,2,2,2,2,2,5,10]", "label": "12.10-2.0.2-2-2-2-2-5-10", "genus": 12, "group": "[10,2]", "_id": {"$oid": "59515cbd3fce4a6697d4dc9d"}}, {"passport_label": "12.10-2.0.2-2-2-2-2-5-10.3", "gen_vectors": [[6, 7, 8, 9, 10, 1, 2, 3, 4, 5], [6, 7, 8, 9, 10, 1, 2, 3, 4, 5], [6, 7, 8, 9, 10, 1, 2, 3, 4, 5], [6, 7, 8, 9, 10, 1, 2, 3, 4, 5], [6, 7, 8, 9, 10, 1, 2, 3, 4, 5], [4, 5, 1, 2, 3, 9, 10, 6, 7, 8], [8, 9, 10, 6, 7, 3, 4, 5, 1, 2]], "total_label": "12.10-2.0.2-2-2-2-2-5-10.3.1", "cc": [3, 1], "signature": "[0,2,2,2,2,2,5,10]", "label": "12.10-2.0.2-2-2-2-2-5-10", "genus": 12, "group": "[10,2]", "_id": {"$oid": "59515cbd3fce4a6697d4dc9e"}}, {"passport_label": "12.10-2.0.2-2-2-2-2-5-10.4", "gen_vectors": [[6, 7, 8, 9, 10, 1, 2, 3, 4, 5], [6, 7, 8, 9, 10, 1, 2, 3, 4, 5], [6, 7, 8, 9, 10, 1, 2, 3, 4, 5], [6, 7, 8, 9, 10, 1, 2, 3, 4, 5], [6, 7, 8, 9, 10, 1, 2, 3, 4, 5], [5, 1, 2, 3, 4, 10, 6, 7, 8, 9], [7, 8, 9, 10, 6, 2, 3, 4, 5, 1]], "total_label": "12.10-2.0.2-2-2-2-2-5-10.4.1", "cc": [4, 1], "signature": "[0,2,2,2,2,2,5,10]", "label": "12.10-2.0.2-2-2-2-2-5-10", "genus": 12, "group": "[10,2]", "_id": {"$oid": "59515cbe3fce4a6697d4dc9f"}}]
[{"passport_label": "12.12-3.0.2-2-2-2-2-3-3.1", "gen_vectors": [[2, 1, 4, 3, 6, 5, 8, 7, 10, 9, 12, 11], [2, 1, 4, 3, 6, 5, 8, 7, 10, 9, 12, 11], [2, 1, 4, 3, 6, 5, 8, 7, 10, 9, 12, 11], [2, 1, 4, 3, 6, 5, 8, 7, 10, 9, 12, 11], [2, 1, 4, 3, 6, 5, 8, 7, 10, 9, 12, 11], [5, 8, 6, 7, 9, 12, 10, 11, 1, 4, 2, 3], [10, 12, 11, 9, 2, 4, 3, 1, 6, 8, 7, 5]], "total_label": "12.12-3.0.2-2-2-2-2-3-3.1.1", "cc": [1, 1], "label": "12.12-3.0.2-2-2-2-2-3-3", "genus": 12, "signature": "[0,2,2,2,2,2,3,3]", "group": "[12,3]", "_id": {"$oid": "59515d533fce4a6697d4ddb2"}}, {"passport_label": "12.12-3.0.2-2-2-2-2-3-3.1", "gen_vectors": [[2, 1, 4, 3, 6, 5, 8, 7, 10, 9, 12, 11], [2, 1, 4, 3, 6, 5, 8, 7, 10, 9, 12, 11], [2, 1, 4, 3, 6, 5, 8, 7, 10, 9, 12, 11], [2, 1, 4, 3, 6, 5, 8, 7, 10, 9, 12, 11], [4, 3, 2, 1, 8, 7, 6, 5, 12, 11, 10, 9], [5, 8, 6, 7, 9, 12, 10, 11, 1, 4, 2, 3], [12, 10, 9, 11, 4, 2, 1, 3, 8, 6, 5, 7]], "total_label": "12.12-3.0.2-2-2-2-2-3-3.1.2", "cc": [1, 2], "label": "12.12-3.0.2-2-2-2-2-3-3", "genus": 12, "signature": "[0,2,2,2,2,2,3,3]", "group": "[12,3]", "_id": {"$oid": "59515d543fce4a6697d4ddb3"}}, {"passport_label": "12.12-3.0.2-2-2-2-2-3-3.1", "gen_vectors": [[2, 1, 4, 3, 6, 5, 8, 7, 10, 9, 12, 11], [2, 1, 4, 3, 6, 5, 8, 7, 10, 9, 12, 11], [2, 1, 4, 3, 6, 5, 8, 7, 10, 9, 12, 11], [2, 1, 4, 3, 6, 5, 8, 7, 10, 9, 12, 11], [3, 4, 1, 2, 7, 8, 5, 6, 11, 12, 9, 10], [5, 8, 6, 7, 9, 12, 10, 11, 1, 4, 2, 3], [11, 9, 10, 12, 3, 1, 2, 4, 7, 5, 6, 8]], "total_label": "12.12-3.0.2-2-2-2-2-3-3.1.3", "cc": [1, 3], "label": "12.12-3.0.2-2-2-2-2-3-3", "genus": 12, "signature": "[0,2,2,2,2,2,3,3]", "group": "[12,3]", "_id": {"$oid": "59515d553fce4a6697d4ddb4"}}, {"passport_label": "12.12-3.0.2-2-2-2-2-3-3.1", "gen_vectors": [[2, 1, 4, 3, 6, 5, 8, 7, 10, 9, 12, 11], [2, 1, 4, 3, 6, 5, 8, 7, 10, 9, 12, 11], [2, 1, 4, 3, 6, 5, 8, 7, 10, 9, 12, 11], [4, 3, 2, 1, 8, 7, 6, 5, 12, 11, 10, 9], [2, 1, 4, 3, 6, 5, 8, 7, 10, 9, 12, 11], [5, 8, 6, 7, 9, 12, 10, 11, 1, 4, 2, 3], [12, 10, 9, 11, 4, 2, 1, 3, 8, 6, 5, 7]], "total_label": "12.12-3.0.2-2-2-2-2-3-3.1.4", "cc": [1, 4], "label": "12.12-3.0.2-2-2-2-2-3-3", "genus": 12, "signature": "[0,2,2,2,2,2,3,3]", "group": "[12,3]", "_id": {"$oid": "59515d553fce4a6697d4ddb5"}}, {"passport_label": "12.12-3.0.2-2-2-2-2-3-3.1", "gen_vectors": [[2, 1, 4, 3, 6, 5, 8, 7, 10, 9, 12, 11], [2, 1, 4, 3, 6, 5, 8, 7, 10, 9, 12, 11], [2, 1, 4, 3, 6, 5, 8, 7, 10, 9, 12, 11], [4, 3, 2, 1, 8, 7, 6, 5, 12, 11, 10, 9], [4, 3, 2, 1, 8, 7, 6, 5, 12, 11, 10, 9], [5, 8, 6, 7, 9, 12, 10, 11, 1, 4, 2, 3], [10, 12, 11, 9, 2, 4, 3, 1, 6, 8, 7, 5]], "total_label": "12.12-3.0.2-2-2-2-2-3-3.1.5", "cc": [1, 5], "label": "12.12-3.0.2-2-2-2-2-3-3", "genus": 12, "signature": "[0,2,2,2,2,2,3,3]", "group": "[12,3]", "_id": {"$oid": "59515d563fce4a6697d4ddb6"}}, {"passport_label": "12.12-3.0.2-2-2-2-2-3-3.1", "gen_vectors": [[2, 1, 4, 3, 6, 5, 8, 7, 10, 9, 12, 11], [2, 1, 4, 3, 6, 5, 8, 7, 10, 9, 12, 11], [2, 1, 4, 3, 6, 5, 8, 7, 10, 9, 12, 11], [4, 3, 2, 1, 8, 7, 6, 5, 12, 11, 10, 9], [3, 4, 1, 2, 7, 8, 5, 6, 11, 12, 9, 10], [5, 8, 6, 7, 9, 12, 10, 11, 1, 4, 2, 3], [9, 11, 12, 10, 1, 3, 4, 2, 5, 7, 8, 6]], "total_label": "12.12-3.0.2-2-2-2-2-3-3.1.6", "cc": [1, 6], "label": "12.12-3.0.2-2-2-2-2-3-3", "genus": 12, "signature": "[0,2,2,2,2,2,3,3]", "group": "[12,3]", "_id": {"$oid": "59515d573fce4a6697d4ddb7"}}, {"passport_label": "12.12-3.0.2-2-2-2-2-3-3.1", "gen_vectors": [[2, 1, 4, 3, 6, 5, 8, 7, 10, 9, 12, 11], [2, 1, 4, 3, 6, 5, 8, 7, 10, 9, 12, 11], [2, 1, 4, 3, 6, 5, 8, 7, 10, 9, 12, 11], [3, 4, 1, 2, 7, 8, 5, 6, 11, 12, 9, 10], [2, 1, 4, 3, 6, 5, 8, 7, 10, 9, 12, 11], [5, 8, 6, 7, 9, 12, 10, 11, 1, 4, 2, 3], [11, 9, 10, 12, 3, 1, 2, 4, 7, 5, 6, 8]], "total_label": "12.12-3.0.2-2-2-2-2-3-3.1.7", "cc": [1, 7], "label": "12.12-3.0.2-2-2-2-2-3-3", "genus": 12, "signature": "[0,2,2,2,2,2,3,3]", "group": "[12,3]", "_id": {"$oid": "59515d573fce4a6697d4ddb8"}}, {"passport_label": "12.12-3.0.2-2-2-2-2-3-3.1", "gen_vectors": [[2, 1, 4, 3, 6, 5, 8, 7, 10, 9, 12, 11], [2, 1, 4, 3, 6, 5, 8, 7, 10, 9, 12, 11], [2, 1, 4, 3, 6, 5, 8, 7, 10, 9, 12, 11], [3, 4, 1, 2, 7, 8, 5, 6, 11, 12, 9, 10], [4, 3, 2, 1, 8, 7, 6, 5, 12, 11, 10, 9], [5, 8, 6, 7, 9, 12, 10, 11, 1, 4, 2, 3], [9, 11, 12, 10, 1, 3, 4, 2, 5, 7, 8, 6]], "total_label": "12.12-3.0.2-2-2-2-2-3-3.1.8", "cc": [1, 8], "label": "12.12-3.0.2-2-2-2-2-3-3", "genus": 12, "signature": "[0,2,2,2,2,2,3,3]", "group": "[12,3]", "_id": {"$oid": "59515d583fce4a6697d4ddb9"}}, {"passport_label": "12.12-3.0.2-2-2-2-2-3-3.1", "gen_vectors": [[2, 1, 4, 3, 6, 5, 8, 7, 10, 9, 12, 11], [2, 1, 4, 3, 6, 5, 8, 7, 10, 9, 12, 11], [2, 1, 4, 3, 6, 5, 8, 7, 10, 9, 12, 11], [3, 4, 1, 2, 7, 8, 5, 6, 11, 12, 9, 10], [3, 4, 1, 2, 7, 8, 5, 6, 11, 12, 9, 10], [5, 8, 6, 7, 9, 12, 10, 11, 1, 4, 2, 3], [10, 12, 11, 9, 2, 4, 3, 1, 6, 8, 7, 5]], "total_label": "12.12-3.0.2-2-2-2-2-3-3.1.9", "cc": [1, 9], "label": "12.12-3.0.2-2-2-2-2-3-3", "genus": 12, "signature": "[0,2,2,2,2,2,3,3]", "group": "[12,3]", "_id": {"$oid": "59515d583fce4a6697d4ddba"}}, {"passport_label": "12.12-3.0.2-2-2-2-2-3-3.1", "gen_vectors": [[2, 1, 4, 3, 6, 5, 8, 7, 10, 9, 12, 11], [2, 1, 4, 3, 6, 5, 8, 7, 10, 9, 12, 11], [4, 3, 2, 1, 8, 7, 6, 5, 12, 11, 10, 9], [2, 1, 4, 3, 6, 5, 8, 7, 10, 9, 12, 11], [2, 1, 4, 3, 6, 5, 8, 7, 10, 9, 12, 11], [5, 8, 6, 7, 9, 12, 10, 11, 1, 4, 2, 3], [12, 10, 9, 11, 4, 2, 1, 3, 8, 6, 5, 7]], "total_label": "12.12-3.0.2-2-2-2-2-3-3.1.10", "cc": [1, 10], "label": "12.12-3.0.2-2-2-2-2-3-3", "genus": 12, "signature": "[0,2,2,2,2,2,3,3]", "group": "[12,3]", "_id": {"$oid": "59515d593fce4a6697d4ddbb"}}, {"passport_label": "12.12-3.0.2-2-2-2-2-3-3.1", "gen_vectors": [[2, 1, 4, 3, 6, 5, 8, 7, 10, 9, 12, 11], [2, 1, 4, 3, 6, 5, 8, 7, 10, 9, 12, 11], [4, 3, 2, 1, 8, 7, 6, 5, 12, 11, 10, 9], [2, 1, 4, 3, 6, 5, 8, 7, 10, 9, 12, 11], [4, 3, 2, 1, 8, 7, 6, 5, 12, 11, 10, 9], [5, 8, 6, 7, 9, 12, 10, 11, 1, 4, 2, 3], [10, 12, 11, 9, 2, 4, 3, 1, 6, 8, 7, 5]], "total_label": "12.12-3.0.2-2-2-2-2-3-3.1.11", "cc": [1, 11], "label": "12.12-3.0.2-2-2-2-2-3-3", "genus": 12, "signature": "[0,2,2,2,2,2,3,3]", "group": "[12,3]", "_id": {"$oid": "59515d593fce4a6697d4ddbc"}}, {"passport_label": "12.12-3.0.2-2-2-2-2-3-3.1", "gen_vectors": [[2, 1, 4, 3, 6, 5, 8, 7, 10, 9, 12, 11], [2, 1, 4, 3, 6, 5, 8, 7, 10, 9, 12, 11], [4, 3, 2, 1, 8, 7, 6, 5, 12, 11, 10, 9], [2, 1, 4, 3, 6, 5, 8, 7, 10, 9, 12, 11], [3, 4, 1, 2, 7, 8, 5, 6, 11, 12, 9, 10], [5, 8, 6, 7, 9, 12, 10, 11, 1, 4, 2, 3], [9, 11, 12, 10, 1, 3, 4, 2, 5, 7, 8, 6]], "total_label": "12.12-3.0.2-2-2-2-2-3-3.1.12", "cc": [1, 12], "label": "12.12-3.0.2-2-2-2-2-3-3", "genus": 12, "signature": "[0,2,2,2,2,2,3,3]", "group": "[12,3]", "_id": {"$oid": "59515d5a3fce4a6697d4ddbd"}}, {"passport_label": "12.12-3.0.2-2-2-2-2-3-3.1", "gen_vectors": [[2, 1, 4, 3, 6, 5, 8, 7, 10, 9, 12, 11], [2, 1, 4, 3, 6, 5, 8, 7, 10, 9, 12, 11], [4, 3, 2, 1, 8, 7, 6, 5, 12, 11, 10, 9], [4, 3, 2, 1, 8, 7, 6, 5, 12, 11, 10, 9], [2, 1, 4, 3, 6, 5, 8, 7, 10, 9, 12, 11], [5, 8, 6, 7, 9, 12, 10, 11, 1, 4, 2, 3], [10, 12, 11, 9, 2, 4, 3, 1, 6, 8, 7, 5]], "total_label": "12.12-3.0.2-2-2-2-2-3-3.1.13", "cc": [1, 13], "label": "12.12-3.0.2-2-2-2-2-3-3", "genus": 12, "signature": "[0,2,2,2,2,2,3,3]", "group": "[12,3]", "_id": {"$oid": "59515d5b3fce4a6697d4ddbe"}}, {"passport_label": "12.12-3.0.2-2-2-2-2-3-3.1", "gen_vectors": [[2, 1, 4, 3, 6, 5, 8, 7, 10, 9, 12, 11], [2, 1, 4, 3, 6, 5, 8, 7, 10, 9, 12, 11], [4, 3, 2, 1, 8, 7, 6, 5, 12, 11, 10, 9], [4, 3, 2, 1, 8, 7, 6, 5, 12, 11, 10, 9], [4, 3, 2, 1, 8, 7, 6, 5, 12, 11, 10, 9], [5, 8, 6, 7, 9, 12, 10, 11, 1, 4, 2, 3], [12, 10, 9, 11, 4, 2, 1, 3, 8, 6, 5, 7]], "total_label": "12.12-3.0.2-2-2-2-2-3-3.1.14", "cc": [1, 14], "label": "12.12-3.0.2-2-2-2-2-3-3", "genus": 12, "signature": "[0,2,2,2,2,2,3,3]", "group": "[12,3]", "_id": {"$oid": "59515d5b3fce4a6697d4ddbf"}}, {"passport_label": "12.12-3.0.2-2-2-2-2-3-3.1", "gen_vectors": [[2, 1, 4, 3, 6, 5, 8, 7, 10, 9, 12, 11], [2, 1, 4, 3, 6, 5, 8, 7, 10, 9, 12, 11], [4, 3, 2, 1, 8, 7, 6, 5, 12, 11, 10, 9], [4, 3, 2, 1, 8, 7, 6, 5, 12, 11, 10, 9], [3, 4, 1, 2, 7, 8, 5, 6, 11, 12, 9, 10], [5, 8, 6, 7, 9, 12, 10, 11, 1, 4, 2, 3], [11, 9, 10, 12, 3, 1, 2, 4, 7, 5, 6, 8]], "total_label": "12.12-3.0.2-2-2-2-2-3-3.1.15", "cc": [1, 15], "label": "12.12-3.0.2-2-2-2-2-3-3", "genus": 12, "signature": "[0,2,2,2,2,2,3,3]", "group": "[12,3]", "_id": {"$oid": "59515d5c3fce4a6697d4ddc0"}}, {"passport_label": "12.12-3.0.2-2-2-2-2-3-3.1", "gen_vectors": [[2, 1, 4, 3, 6, 5, 8, 7, 10, 9, 12, 11], [2, 1, 4, 3, 6, 5, 8, 7, 10, 9, 12, 11], [4, 3, 2, 1, 8, 7, 6, 5, 12, 11, 10, 9], [3, 4, 1, 2, 7, 8, 5, 6, 11, 12, 9, 10], [2, 1, 4, 3, 6, 5, 8, 7, 10, 9, 12, 11], [5, 8, 6, 7, 9, 12, 10, 11, 1, 4, 2, 3], [9, 11, 12, 10, 1, 3, 4, 2, 5, 7, 8, 6]], "total_label": "12.12-3.0.2-2-2-2-2-3-3.1.16", "cc": [1, 16], "label": "12.12-3.0.2-2-2-2-2-3-3", "genus": 12, "signature": "[0,2,2,2,2,2,3,3]", "group": "[12,3]", "_id": {"$oid": "59515d5c3fce4a6697d4ddc1"}}, {"passport_label": "12.12-3.0.2-2-2-2-2-3-3.1", "gen_vectors": [[2, 1, 4, 3, 6, 5, 8, 7, 10, 9, 12, 11], [2, 1, 4, 3, 6, 5, 8, 7, 10, 9, 12, 11], [4, 3, 2, 1, 8, 7, 6, 5, 12, 11, 10, 9], [3, 4, 1, 2, 7, 8, 5, 6, 11, 12, 9, 10], [4, 3, 2, 1, 8, 7, 6, 5, 12, 11, 10, 9], [5, 8, 6, 7, 9, 12, 10, 11, 1, 4, 2, 3], [11, 9, 10, 12, 3, 1, 2, 4, 7, 5, 6, 8]], "total_label": "12.12-3.0.2-2-2-2-2-3-3.1.17", "cc": [1, 17], "label": "12.12-3.0.2-2-2-2-2-3-3", "genus": 12, "signature": "[0,2,2,2,2,2,3,3]", "group": "[12,3]", "_id": {"$oid": "59515d5c3fce4a6697d4ddc2"}}, {"passport_label": "12.12-3.0.2-2-2-2-2-3-3.1", "gen_vectors": [[2, 1, 4, 3, 6, 5, 8, 7, 10, 9, 12, 11], [2, 1, 4, 3, 6, 5, 8, 7, 10, 9, 12, 11], [4, 3, 2, 1, 8, 7, 6, 5, 12, 11, 10, 9], [3, 4, 1, 2, 7, 8, 5, 6, 11, 12, 9, 10], [3, 4, 1, 2, 7, 8, 5, 6, 11, 12, 9, 10], [5, 8, 6, 7, 9, 12, 10, 11, 1, 4, 2, 3], [12, 10, 9, 11, 4, 2, 1, 3, 8, 6, 5, 7]], "total_label": "12.12-3.0.2-2-2-2-2-3-3.1.18", "cc": [1, 18], "label": "12.12-3.0.2-2-2-2-2-3-3", "genus": 12, "signature": "[0,2,2,2,2,2,3,3]", "group": "[12,3]", "_id": {"$oid": "59515d5d3fce4a6697d4ddc3"}}, {"passport_label": "12.12-3.0.2-2-2-2-2-3-3.1", "gen_vectors": [[2, 1, 4, 3, 6, 5, 8, 7, 10, 9, 12, 11], [2, 1, 4, 3, 6, 5, 8, 7, 10, 9, 12, 11], [3, 4, 1, 2, 7, 8, 5, 6, 11, 12, 9, 10], [2, 1, 4, 3, 6, 5, 8, 7, 10, 9, 12, 11], [2, 1, 4, 3, 6, 5, 8, 7, 10, 9, 12, 11], [5, 8, 6, 7, 9, 12, 10, 11, 1, 4, 2, 3], [11, 9, 10, 12, 3, 1, 2, 4, 7, 5, 6, 8]], "total_label": "12.12-3.0.2-2-2-2-2-3-3.1.19", "cc": [1, 19], "label": "12.12-3.0.2-2-2-2-2-3-3", "genus": 12, "signature": "[0,2,2,2,2,2,3,3]", "group": "[12,3]", "_id": {"$oid": "59515d5d3fce4a6697d4ddc4"}}, {"passport_label": "12.12-3.0.2-2-2-2-2-3-3.1", "gen_vectors": [[2, 1, 4, 3, 6, 5, 8, 7, 10, 9, 12, 11], [2, 1, 4, 3, 6, 5, 8, 7, 10, 9, 12, 11], [3, 4, 1, 2, 7, 8, 5, 6, 11, 12, 9, 10], [2, 1, 4, 3, 6, 5, 8, 7, 10, 9, 12, 11], [4, 3, 2, 1, 8, 7, 6, 5, 12, 11, 10, 9], [5, 8, 6, 7, 9, 12, 10, 11, 1, 4, 2, 3], [9, 11, 12, 10, 1, 3, 4, 2, 5, 7, 8, 6]], "total_label": "12.12-3.0.2-2-2-2-2-3-3.1.20", "cc": [1, 20], "label": "12.12-3.0.2-2-2-2-2-3-3", "genus": 12, "signature": "[0,2,2,2,2,2,3,3]", "group": "[12,3]", "_id": {"$oid": "59515d5e3fce4a6697d4ddc5"}}, {"passport_label": "12.12-3.0.2-2-2-2-2-3-3.1", "gen_vectors": [[2, 1, 4, 3, 6, 5, 8, 7, 10, 9, 12, 11], [2, 1, 4, 3, 6, 5, 8, 7, 10, 9, 12, 11], [3, 4, 1, 2, 7, 8, 5, 6, 11, 12, 9, 10], [2, 1, 4, 3, 6, 5, 8, 7, 10, 9, 12, 11], [3, 4, 1, 2, 7, 8, 5, 6, 11, 12, 9, 10], [5, 8, 6, 7, 9, 12, 10, 11, 1, 4, 2, 3], [10, 12, 11, 9, 2, 4, 3, 1, 6, 8, 7, 5]], "total_label": "12.12-3.0.2-2-2-2-2-3-3.1.21", "cc": [1, 21], "label": "12.12-3.0.2-2-2-2-2-3-3", "genus": 12, "signature": "[0,2,2,2,2,2,3,3]", "group": "[12,3]", "_id": {"$oid": "59515d5e3fce4a6697d4ddc6"}}, {"passport_label": "12.12-3.0.2-2-2-2-2-3-3.1", "gen_vectors": [[2, 1, 4, 3, 6, 5, 8, 7, 10, 9, 12, 11], [2, 1, 4, 3, 6, 5, 8, 7, 10, 9, 12, 11], [3, 4, 1, 2, 7, 8, 5, 6, 11, 12, 9, 10], [4, 3, 2, 1, 8, 7, 6, 5, 12, 11, 10, 9], [2, 1, 4, 3, 6, 5, 8, 7, 10, 9, 12, 11], [5, 8, 6, 7, 9, 12, 10, 11, 1, 4, 2, 3], [9, 11, 12, 10, 1, 3, 4, 2, 5, 7, 8, 6]], "total_label": "12.12-3.0.2-2-2-2-2-3-3.1.22", "cc": [1, 22], "label": "12.12-3.0.2-2-2-2-2-3-3", "genus": 12, "signature": "[0,2,2,2,2,2,3,3]", "group": "[12,3]", "_id": {"$oid": "59515d5f3fce4a6697d4ddc7"}}, {"passport_label": "12.12-3.0.2-2-2-2-2-3-3.1", "gen_vectors": [[2, 1, 4, 3, 6, 5, 8, 7, 10, 9, 12, 11], [2, 1, 4, 3, 6, 5, 8, 7, 10, 9, 12, 11], [3, 4, 1, 2, 7, 8, 5, 6, 11, 12, 9, 10], [4, 3, 2, 1, 8, 7, 6, 5, 12, 11, 10, 9], [4, 3, 2, 1, 8, 7, 6, 5, 12, 11, 10, 9], [5, 8, 6, 7, 9, 12, 10, 11, 1, 4, 2, 3], [11, 9, 10, 12, 3, 1, 2, 4, 7, 5, 6, 8]], "total_label": "12.12-3.0.2-2-2-2-2-3-3.1.23", "cc": [1, 23], "label": "12.12-3.0.2-2-2-2-2-3-3", "genus": 12, "signature": "[0,2,2,2,2,2,3,3]", "group": "[12,3]", "_id": {"$oid": "59515d603fce4a6697d4ddc8"}}, {"passport_label": "12.12-3.0.2-2-2-2-2-3-3.1", "gen_vectors": [[2, 1, 4, 3, 6, 5, 8, 7, 10, 9, 12, 11], [2, 1, 4, 3, 6, 5, 8, 7, 10, 9, 12, 11], [3, 4, 1, 2, 7, 8, 5, 6, 11, 12, 9, 10], [4, 3, 2, 1, 8, 7, 6, 5, 12, 11, 10, 9], [3, 4, 1, 2, 7, 8, 5, 6, 11, 12, 9, 10], [5, 8, 6, 7, 9, 12, 10, 11, 1, 4, 2, 3], [12, 10, 9, 11, 4, 2, 1, 3, 8, 6, 5, 7]], "total_label": "12.12-3.0.2-2-2-2-2-3-3.1.24", "cc": [1, 24], "label": "12.12-3.0.2-2-2-2-2-3-3", "genus": 12, "signature": "[0,2,2,2,2,2,3,3]", "group": "[12,3]", "_id": {"$oid": "59515d603fce4a6697d4ddc9"}}, {"passport_label": "12.12-3.0.2-2-2-2-2-3-3.1", "gen_vectors": [[2, 1, 4, 3, 6, 5, 8, 7, 10, 9, 12, 11], [2, 1, 4, 3, 6, 5, 8, 7, 10, 9, 12, 11], [3, 4, 1, 2, 7, 8, 5, 6, 11, 12, 9, 10], [3, 4, 1, 2, 7, 8, 5, 6, 11, 12, 9, 10], [2, 1, 4, 3, 6, 5, 8, 7, 10, 9, 12, 11], [5, 8, 6, 7, 9, 12, 10, 11, 1, 4, 2, 3], [10, 12, 11, 9, 2, 4, 3, 1, 6, 8, 7, 5]], "total_label": "12.12-3.0.2-2-2-2-2-3-3.1.25", "cc": [1, 25], "label": "12.12-3.0.2-2-2-2-2-3-3", "genus": 12, "signature": "[0,2,2,2,2,2,3,3]", "group": "[12,3]", "_id": {"$oid": "59515d603fce4a6697d4ddca"}}, {"passport_label": "12.12-3.0.2-2-2-2-2-3-3.1", "gen_vectors": [[2, 1, 4, 3, 6, 5, 8, 7, 10, 9, 12, 11], [2, 1, 4, 3, 6, 5, 8, 7, 10, 9, 12, 11], [3, 4, 1, 2, 7, 8, 5, 6, 11, 12, 9, 10], [3, 4, 1, 2, 7, 8, 5, 6, 11, 12, 9, 10], [4, 3, 2, 1, 8, 7, 6, 5, 12, 11, 10, 9], [5, 8, 6, 7, 9, 12, 10, 11, 1, 4, 2, 3], [12, 10, 9, 11, 4, 2, 1, 3, 8, 6, 5, 7]], "total_label": "12.12-3.0.2-2-2-2-2-3-3.1.26", "cc": [1, 26], "label": "12.12-3.0.2-2-2-2-2-3-3", "genus": 12, "signature": "[0,2,2,2,2,2,3,3]", "group": "[12,3]", "_id": {"$oid": "59515d613fce4a6697d4ddcb"}}, {"passport_label": "12.12-3.0.2-2-2-2-2-3-3.1", "gen_vectors": [[2, 1, 4, 3, 6, 5, 8, 7, 10, 9, 12, 11], [2, 1, 4, 3, 6, 5, 8, 7, 10, 9, 12, 11], [3, 4, 1, 2, 7, 8, 5, 6, 11, 12, 9, 10], [3, 4, 1, 2, 7, 8, 5, 6, 11, 12, 9, 10], [3, 4, 1, 2, 7, 8, 5, 6, 11, 12, 9, 10], [5, 8, 6, 7, 9, 12, 10, 11, 1, 4, 2, 3], [11, 9, 10, 12, 3, 1, 2, 4, 7, 5, 6, 8]], "total_label": "12.12-3.0.2-2-2-2-2-3-3.1.27", "cc": [1, 27], "label": "12.12-3.0.2-2-2-2-2-3-3", "genus": 12, "signature": "[0,2,2,2,2,2,3,3]", "group": "[12,3]", "_id": {"$oid": "59515d623fce4a6697d4ddcc"}}, {"passport_label": "12.12-3.0.2-2-2-2-2-3-3.1", "gen_vectors": [[2, 1, 4, 3, 6, 5, 8, 7, 10, 9, 12, 11], [4, 3, 2, 1, 8, 7, 6, 5, 12, 11, 10, 9], [2, 1, 4, 3, 6, 5, 8, 7, 10, 9, 12, 11], [2, 1, 4, 3, 6, 5, 8, 7, 10, 9, 12, 11], [2, 1, 4, 3, 6, 5, 8, 7, 10, 9, 12, 11], [5, 8, 6, 7, 9, 12, 10, 11, 1, 4, 2, 3], [12, 10, 9, 11, 4, 2, 1, 3, 8, 6, 5, 7]], "total_label": "12.12-3.0.2-2-2-2-2-3-3.1.28", "cc": [1, 28], "label": "12.12-3.0.2-2-2-2-2-3-3", "genus": 12, "signature": "[0,2,2,2,2,2,3,3]", "group": "[12,3]", "_id": {"$oid": "59515d623fce4a6697d4ddcd"}}, {"passport_label": "12.12-3.0.2-2-2-2-2-3-3.1", "gen_vectors": [[2, 1, 4, 3, 6, 5, 8, 7, 10, 9, 12, 11], [4, 3, 2, 1, 8, 7, 6, 5, 12, 11, 10, 9], [2, 1, 4, 3, 6, 5, 8, 7, 10, 9, 12, 11], [2, 1, 4, 3, 6, 5, 8, 7, 10, 9, 12, 11], [4, 3, 2, 1, 8, 7, 6, 5, 12, 11, 10, 9], [5, 8, 6, 7, 9, 12, 10, 11, 1, 4, 2, 3], [10, 12, 11, 9, 2, 4, 3, 1, 6, 8, 7, 5]], "total_label": "12.12-3.0.2-2-2-2-2-3-3.1.29", "cc": [1, 29], "label": "12.12-3.0.2-2-2-2-2-3-3", "genus": 12, "signature": "[0,2,2,2,2,2,3,3]", "group": "[12,3]", "_id": {"$oid": "59515d633fce4a6697d4ddce"}}, {"passport_label": "12.12-3.0.2-2-2-2-2-3-3.1", "gen_vectors": [[2, 1, 4, 3, 6, 5, 8, 7, 10, 9, 12, 11], [4, 3, 2, 1, 8, 7, 6, 5, 12, 11, 10, 9], [2, 1, 4, 3, 6, 5, 8, 7, 10, 9, 12, 11], [2, 1, 4, 3, 6, 5, 8, 7, 10, 9, 12, 11], [3, 4, 1, 2, 7, 8, 5, 6, 11, 12, 9, 10], [5, 8, 6, 7, 9, 12, 10, 11, 1, 4, 2, 3], [9, 11, 12, 10, 1, 3, 4, 2, 5, 7, 8, 6]], "total_label": "12.12-3.0.2-2-2-2-2-3-3.1.30", "cc": [1, 30], "label": "12.12-3.0.2-2-2-2-2-3-3", "genus": 12, "signature": "[0,2,2,2,2,2,3,3]", "group": "[12,3]", "_id": {"$oid": "59515d633fce4a6697d4ddcf"}}, {"passport_label": "12.12-3.0.2-2-2-2-2-3-3.1", "gen_vectors": [[2, 1, 4, 3, 6, 5, 8, 7, 10, 9, 12, 11], [4, 3, 2, 1, 8, 7, 6, 5, 12, 11, 10, 9], [2, 1, 4, 3, 6, 5, 8, 7, 10, 9, 12, 11], [4, 3, 2, 1, 8, 7, 6, 5, 12, 11, 10, 9], [2, 1, 4, 3, 6, 5, 8, 7, 10, 9, 12, 11], [5, 8, 6, 7, 9, 12, 10, 11, 1, 4, 2, 3], [10, 12, 11, 9, 2, 4, 3, 1, 6, 8, 7, 5]], "total_label": "12.12-3.0.2-2-2-2-2-3-3.1.31", "cc": [1, 31], "label": "12.12-3.0.2-2-2-2-2-3-3", "genus": 12, "signature": "[0,2,2,2,2,2,3,3]", "group": "[12,3]", "_id": {"$oid": "59515d643fce4a6697d4ddd0"}}, {"passport_label": "12.12-3.0.2-2-2-2-2-3-3.1", "gen_vectors": [[2, 1, 4, 3, 6, 5, 8, 7, 10, 9, 12, 11], [4, 3, 2, 1, 8, 7, 6, 5, 12, 11, 10, 9], [2, 1, 4, 3, 6, 5, 8, 7, 10, 9, 12, 11], [4, 3, 2, 1, 8, 7, 6, 5, 12, 11, 10, 9], [4, 3, 2, 1, 8, 7, 6, 5, 12, 11, 10, 9], [5, 8, 6, 7, 9, 12, 10, 11, 1, 4, 2, 3], [12, 10, 9, 11, 4, 2, 1, 3, 8, 6, 5, 7]], "total_label": "12.12-3.0.2-2-2-2-2-3-3.1.32", "cc": [1, 32], "label": "12.12-3.0.2-2-2-2-2-3-3", "genus": 12, "signature": "[0,2,2,2,2,2,3,3]", "group": "[12,3]", "_id": {"$oid": "59515d643fce4a6697d4ddd1"}}, {"passport_label": "12.12-3.0.2-2-2-2-2-3-3.1", "gen_vectors": [[2, 1, 4, 3, 6, 5, 8, 7, 10, 9, 12, 11], [4, 3, 2, 1, 8, 7, 6, 5, 12, 11, 10, 9], [2, 1, 4, 3, 6, 5, 8, 7, 10, 9, 12, 11], [4, 3, 2, 1, 8, 7, 6, 5, 12, 11, 10, 9], [3, 4, 1, 2, 7, 8, 5, 6, 11, 12, 9, 10], [5, 8, 6, 7, 9, 12, 10, 11, 1, 4, 2, 3], [11, 9, 10, 12, 3, 1, 2, 4, 7, 5, 6, 8]], "total_label": "12.12-3.0.2-2-2-2-2-3-3.1.33", "cc": [1, 33], "label": "12.12-3.0.2-2-2-2-2-3-3", "genus": 12, "signature": "[0,2,2,2,2,2,3,3]", "group": "[12,3]", "_id": {"$oid": "59515d653fce4a6697d4ddd2"}}, {"passport_label": "12.12-3.0.2-2-2-2-2-3-3.1", "gen_vectors": [[2, 1, 4, 3, 6, 5, 8, 7, 10, 9, 12, 11], [4, 3, 2, 1, 8, 7, 6, 5, 12, 11, 10, 9], [2, 1, 4, 3, 6, 5, 8, 7, 10, 9, 12, 11], [3, 4, 1, 2, 7, 8, 5, 6, 11, 12, 9, 10], [2, 1, 4, 3, 6, 5, 8, 7, 10, 9, 12, 11], [5, 8, 6, 7, 9, 12, 10, 11, 1, 4, 2, 3], [9, 11, 12, 10, 1, 3, 4, 2, 5, 7, 8, 6]], "total_label": "12.12-3.0.2-2-2-2-2-3-3.1.34", "cc": [1, 34], "label": "12.12-3.0.2-2-2-2-2-3-3", "genus": 12, "signature": "[0,2,2,2,2,2,3,3]", "group": "[12,3]", "_id": {"$oid": "59515d663fce4a6697d4ddd3"}}, {"passport_label": "12.12-3.0.2-2-2-2-2-3-3.1", "gen_vectors": [[2, 1, 4, 3, 6, 5, 8, 7, 10, 9, 12, 11], [4, 3, 2, 1, 8, 7, 6, 5, 12, 11, 10, 9], [2, 1, 4, 3, 6, 5, 8, 7, 10, 9, 12, 11], [3, 4, 1, 2, 7, 8, 5, 6, 11, 12, 9, 10], [4, 3, 2, 1, 8, 7, 6, 5, 12, 11, 10, 9], [5, 8, 6, 7, 9, 12, 10, 11, 1, 4, 2, 3], [11, 9, 10, 12, 3, 1, 2, 4, 7, 5, 6, 8]], "total_label": "12.12-3.0.2-2-2-2-2-3-3.1.35", "cc": [1, 35], "label": "12.12-3.0.2-2-2-2-2-3-3", "genus": 12, "signature": "[0,2,2,2,2,2,3,3]", "group": "[12,3]", "_id": {"$oid": "59515d663fce4a6697d4ddd4"}}, {"passport_label": "12.12-3.0.2-2-2-2-2-3-3.1", "gen_vectors": [[2, 1, 4, 3, 6, 5, 8, 7, 10, 9, 12, 11], [4, 3, 2, 1, 8, 7, 6, 5, 12, 11, 10, 9], [2, 1, 4, 3, 6, 5, 8, 7, 10, 9, 12, 11], [3, 4, 1, 2, 7, 8, 5, 6, 11, 12, 9, 10], [3, 4, 1, 2, 7, 8, 5, 6, 11, 12, 9, 10], [5, 8, 6, 7, 9, 12, 10, 11, 1, 4, 2, 3], [12, 10, 9, 11, 4, 2, 1, 3, 8, 6, 5, 7]], "total_label": "12.12-3.0.2-2-2-2-2-3-3.1.36", "cc": [1, 36], "label": "12.12-3.0.2-2-2-2-2-3-3", "genus": 12, "signature": "[0,2,2,2,2,2,3,3]", "group": "[12,3]", "_id": {"$oid": "59515d673fce4a6697d4ddd5"}}, {"passport_label": "12.12-3.0.2-2-2-2-2-3-3.1", "gen_vectors": [[2, 1, 4, 3, 6, 5, 8, 7, 10, 9, 12, 11], [4, 3, 2, 1, 8, 7, 6, 5, 12, 11, 10, 9], [4, 3, 2, 1, 8, 7, 6, 5, 12, 11, 10, 9], [2, 1, 4, 3, 6, 5, 8, 7, 10, 9, 12, 11], [2, 1, 4, 3, 6, 5, 8, 7, 10, 9, 12, 11], [5, 8, 6, 7, 9, 12, 10, 11, 1, 4, 2, 3], [10, 12, 11, 9, 2, 4, 3, 1, 6, 8, 7, 5]], "total_label": "12.12-3.0.2-2-2-2-2-3-3.1.37", "cc": [1, 37], "label": "12.12-3.0.2-2-2-2-2-3-3", "genus": 12, "signature": "[0,2,2,2,2,2,3,3]", "group": "[12,3]", "_id": {"$oid": "59515d673fce4a6697d4ddd6"}}, {"passport_label": "12.12-3.0.2-2-2-2-2-3-3.1", "gen_vectors": [[2, 1, 4, 3, 6, 5, 8, 7, 10, 9, 12, 11], [4, 3, 2, 1, 8, 7, 6, 5, 12, 11, 10, 9], [4, 3, 2, 1, 8, 7, 6, 5, 12, 11, 10, 9], [2, 1, 4, 3, 6, 5, 8, 7, 10, 9, 12, 11], [4, 3, 2, 1, 8, 7, 6, 5, 12, 11, 10, 9], [5, 8, 6, 7, 9, 12, 10, 11, 1, 4, 2, 3], [12, 10, 9, 11, 4, 2, 1, 3, 8, 6, 5, 7]], "total_label": "12.12-3.0.2-2-2-2-2-3-3.1.38", "cc": [1, 38], "label": "12.12-3.0.2-2-2-2-2-3-3", "genus": 12, "signature": "[0,2,2,2,2,2,3,3]", "group": "[12,3]", "_id": {"$oid": "59515d683fce4a6697d4ddd7"}}, {"passport_label": "12.12-3.0.2-2-2-2-2-3-3.1", "gen_vectors": [[2, 1, 4, 3, 6, 5, 8, 7, 10, 9, 12, 11], [4, 3, 2, 1, 8, 7, 6, 5, 12, 11, 10, 9], [4, 3, 2, 1, 8, 7, 6, 5, 12, 11, 10, 9], [2, 1, 4, 3, 6, 5, 8, 7, 10, 9, 12, 11], [3, 4, 1, 2, 7, 8, 5, 6, 11, 12, 9, 10], [5, 8, 6, 7, 9, 12, 10, 11, 1, 4, 2, 3], [11, 9, 10, 12, 3, 1, 2, 4, 7, 5, 6, 8]], "total_label": "12.12-3.0.2-2-2-2-2-3-3.1.39", "cc": [1, 39], "label": "12.12-3.0.2-2-2-2-2-3-3", "genus": 12, "signature": "[0,2,2,2,2,2,3,3]", "group": "[12,3]", "_id": {"$oid": "59515d683fce4a6697d4ddd8"}}, {"passport_label": "12.12-3.0.2-2-2-2-2-3-3.1", "gen_vectors": [[2, 1, 4, 3, 6, 5, 8, 7, 10, 9, 12, 11], [4, 3, 2, 1, 8, 7, 6, 5, 12, 11, 10, 9], [4, 3, 2, 1, 8, 7, 6, 5, 12, 11, 10, 9], [4, 3, 2, 1, 8, 7, 6, 5, 12, 11, 10, 9], [2, 1, 4, 3, 6, 5, 8, 7, 10, 9, 12, 11], [5, 8, 6, 7, 9, 12, 10, 11, 1, 4, 2, 3], [12, 10, 9, 11, 4, 2, 1, 3, 8, 6, 5, 7]], "total_label": "12.12-3.0.2-2-2-2-2-3-3.1.40", "cc": [1, 40], "label": "12.12-3.0.2-2-2-2-2-3-3", "genus": 12, "signature": "[0,2,2,2,2,2,3,3]", "group": "[12,3]", "_id": {"$oid": "59515d683fce4a6697d4ddd9"}}, {"passport_label": "12.12-3.0.2-2-2-2-2-3-3.1", "gen_vectors": [[2, 1, 4, 3, 6, 5, 8, 7, 10, 9, 12, 11], [4, 3, 2, 1, 8, 7, 6, 5, 12, 11, 10, 9], [4, 3, 2, 1, 8, 7, 6, 5, 12, 11, 10, 9], [4, 3, 2, 1, 8, 7, 6, 5, 12, 11, 10, 9], [4, 3, 2, 1, 8, 7, 6, 5, 12, 11, 10, 9], [5, 8, 6, 7, 9, 12, 10, 11, 1, 4, 2, 3], [10, 12, 11, 9, 2, 4, 3, 1, 6, 8, 7, 5]], "total_label": "12.12-3.0.2-2-2-2-2-3-3.1.41", "cc": [1, 41], "label": "12.12-3.0.2-2-2-2-2-3-3", "genus": 12, "signature": "[0,2,2,2,2,2,3,3]", "group": "[12,3]", "_id": {"$oid": "59515d693fce4a6697d4ddda"}}, {"passport_label": "12.12-3.0.2-2-2-2-2-3-3.1", "gen_vectors": [[2, 1, 4, 3, 6, 5, 8, 7, 10, 9, 12, 11], [4, 3, 2, 1, 8, 7, 6, 5, 12, 11, 10, 9], [4, 3, 2, 1, 8, 7, 6, 5, 12, 11, 10, 9], [4, 3, 2, 1, 8, 7, 6, 5, 12, 11, 10, 9], [3, 4, 1, 2, 7, 8, 5, 6, 11, 12, 9, 10], [5, 8, 6, 7, 9, 12, 10, 11, 1, 4, 2, 3], [9, 11, 12, 10, 1, 3, 4, 2, 5, 7, 8, 6]], "total_label": "12.12-3.0.2-2-2-2-2-3-3.1.42", "cc": [1, 42], "label": "12.12-3.0.2-2-2-2-2-3-3", "genus": 12, "signature": "[0,2,2,2,2,2,3,3]", "group": "[12,3]", "_id": {"$oid": "59515d6a3fce4a6697d4dddb"}}, {"passport_label": "12.12-3.0.2-2-2-2-2-3-3.1", "gen_vectors": [[2, 1, 4, 3, 6, 5, 8, 7, 10, 9, 12, 11], [4, 3, 2, 1, 8, 7, 6, 5, 12, 11, 10, 9], [4, 3, 2, 1, 8, 7, 6, 5, 12, 11, 10, 9], [3, 4, 1, 2, 7, 8, 5, 6, 11, 12, 9, 10], [2, 1, 4, 3, 6, 5, 8, 7, 10, 9, 12, 11], [5, 8, 6, 7, 9, 12, 10, 11, 1, 4, 2, 3], [11, 9, 10, 12, 3, 1, 2, 4, 7, 5, 6, 8]], "total_label": "12.12-3.0.2-2-2-2-2-3-3.1.43", "cc": [1, 43], "label": "12.12-3.0.2-2-2-2-2-3-3", "genus": 12, "signature": "[0,2,2,2,2,2,3,3]", "group": "[12,3]", "_id": {"$oid": "59515d6a3fce4a6697d4dddc"}}, {"passport_label": "12.12-3.0.2-2-2-2-2-3-3.1", "gen_vectors": [[2, 1, 4, 3, 6, 5, 8, 7, 10, 9, 12, 11], [4, 3, 2, 1, 8, 7, 6, 5, 12, 11, 10, 9], [4, 3, 2, 1, 8, 7, 6, 5, 12, 11, 10, 9], [3, 4, 1, 2, 7, 8, 5, 6, 11, 12, 9, 10], [4, 3, 2, 1, 8, 7, 6, 5, 12, 11, 10, 9], [5, 8, 6, 7, 9, 12, 10, 11, 1, 4, 2, 3], [9, 11, 12, 10, 1, 3, 4, 2, 5, 7, 8, 6]], "total_label": "12.12-3.0.2-2-2-2-2-3-3.1.44", "cc": [1, 44], "label": "12.12-3.0.2-2-2-2-2-3-3", "genus": 12, "signature": "[0,2,2,2,2,2,3,3]", "group": "[12,3]", "_id": {"$oid": "59515d6b3fce4a6697d4dddd"}}, {"passport_label": "12.12-3.0.2-2-2-2-2-3-3.1", "gen_vectors": [[2, 1, 4, 3, 6, 5, 8, 7, 10, 9, 12, 11], [4, 3, 2, 1, 8, 7, 6, 5, 12, 11, 10, 9], [4, 3, 2, 1, 8, 7, 6, 5, 12, 11, 10, 9], [3, 4, 1, 2, 7, 8, 5, 6, 11, 12, 9, 10], [3, 4, 1, 2, 7, 8, 5, 6, 11, 12, 9, 10], [5, 8, 6, 7, 9, 12, 10, 11, 1, 4, 2, 3], [10, 12, 11, 9, 2, 4, 3, 1, 6, 8, 7, 5]], "total_label": "12.12-3.0.2-2-2-2-2-3-3.1.45", "cc": [1, 45], "label": "12.12-3.0.2-2-2-2-2-3-3", "genus": 12, "signature": "[0,2,2,2,2,2,3,3]", "group": "[12,3]", "_id": {"$oid": "59515d6b3fce4a6697d4ddde"}}, {"passport_label": "12.12-3.0.2-2-2-2-2-3-3.1", "gen_vectors": [[2, 1, 4, 3, 6, 5, 8, 7, 10, 9, 12, 11], [4, 3, 2, 1, 8, 7, 6, 5, 12, 11, 10, 9], [3, 4, 1, 2, 7, 8, 5, 6, 11, 12, 9, 10], [2, 1, 4, 3, 6, 5, 8, 7, 10, 9, 12, 11], [2, 1, 4, 3, 6, 5, 8, 7, 10, 9, 12, 11], [5, 8, 6, 7, 9, 12, 10, 11, 1, 4, 2, 3], [9, 11, 12, 10, 1, 3, 4, 2, 5, 7, 8, 6]], "total_label": "12.12-3.0.2-2-2-2-2-3-3.1.46", "cc": [1, 46], "label": "12.12-3.0.2-2-2-2-2-3-3", "genus": 12, "signature": "[0,2,2,2,2,2,3,3]", "group": "[12,3]", "_id": {"$oid": "59515d6c3fce4a6697d4dddf"}}, {"passport_label": "12.12-3.0.2-2-2-2-2-3-3.1", "gen_vectors": [[2, 1, 4, 3, 6, 5, 8, 7, 10, 9, 12, 11], [4, 3, 2, 1, 8, 7, 6, 5, 12, 11, 10, 9], [3, 4, 1, 2, 7, 8, 5, 6, 11, 12, 9, 10], [2, 1, 4, 3, 6, 5, 8, 7, 10, 9, 12, 11], [4, 3, 2, 1, 8, 7, 6, 5, 12, 11, 10, 9], [5, 8, 6, 7, 9, 12, 10, 11, 1, 4, 2, 3], [11, 9, 10, 12, 3, 1, 2, 4, 7, 5, 6, 8]], "total_label": "12.12-3.0.2-2-2-2-2-3-3.1.47", "cc": [1, 47], "label": "12.12-3.0.2-2-2-2-2-3-3", "genus": 12, "signature": "[0,2,2,2,2,2,3,3]", "group": "[12,3]", "_id": {"$oid": "59515d6c3fce4a6697d4dde0"}}, {"passport_label": "12.12-3.0.2-2-2-2-2-3-3.1", "gen_vectors": [[2, 1, 4, 3, 6, 5, 8, 7, 10, 9, 12, 11], [4, 3, 2, 1, 8, 7, 6, 5, 12, 11, 10, 9], [3, 4, 1, 2, 7, 8, 5, 6, 11, 12, 9, 10], [2, 1, 4, 3, 6, 5, 8, 7, 10, 9, 12, 11], [3, 4, 1, 2, 7, 8, 5, 6, 11, 12, 9, 10], [5, 8, 6, 7, 9, 12, 10, 11, 1, 4, 2, 3], [12, 10, 9, 11, 4, 2, 1, 3, 8, 6, 5, 7]], "total_label": "12.12-3.0.2-2-2-2-2-3-3.1.48", "cc": [1, 48], "label": "12.12-3.0.2-2-2-2-2-3-3", "genus": 12, "signature": "[0,2,2,2,2,2,3,3]", "group": "[12,3]", "_id": {"$oid": "59515d6d3fce4a6697d4dde1"}}, {"passport_label": "12.12-3.0.2-2-2-2-2-3-3.1", "gen_vectors": [[2, 1, 4, 3, 6, 5, 8, 7, 10, 9, 12, 11], [4, 3, 2, 1, 8, 7, 6, 5, 12, 11, 10, 9], [3, 4, 1, 2, 7, 8, 5, 6, 11, 12, 9, 10], [4, 3, 2, 1, 8, 7, 6, 5, 12, 11, 10, 9], [2, 1, 4, 3, 6, 5, 8, 7, 10, 9, 12, 11], [5, 8, 6, 7, 9, 12, 10, 11, 1, 4, 2, 3], [11, 9, 10, 12, 3, 1, 2, 4, 7, 5, 6, 8]], "total_label": "12.12-3.0.2-2-2-2-2-3-3.1.49", "cc": [1, 49], "label": "12.12-3.0.2-2-2-2-2-3-3", "genus": 12, "signature": "[0,2,2,2,2,2,3,3]", "group": "[12,3]", "_id": {"$oid": "59515d6d3fce4a6697d4dde2"}}, {"passport_label": "12.12-3.0.2-2-2-2-2-3-3.1", "gen_vectors": [[2, 1, 4, 3, 6, 5, 8, 7, 10, 9, 12, 11], [4, 3, 2, 1, 8, 7, 6, 5, 12, 11, 10, 9], [3, 4, 1, 2, 7, 8, 5, 6, 11, 12, 9, 10], [4, 3, 2, 1, 8, 7, 6, 5, 12, 11, 10, 9], [4, 3, 2, 1, 8, 7, 6, 5, 12, 11, 10, 9], [5, 8, 6, 7, 9, 12, 10, 11, 1, 4, 2, 3], [9, 11, 12, 10, 1, 3, 4, 2, 5, 7, 8, 6]], "total_label": "12.12-3.0.2-2-2-2-2-3-3.1.50", "cc": [1, 50], "label": "12.12-3.0.2-2-2-2-2-3-3", "genus": 12, "signature": "[0,2,2,2,2,2,3,3]", "group": "[12,3]", "_id": {"$oid": "59515d6e3fce4a6697d4dde3"}}, {"passport_label": "12.12-3.0.2-2-2-2-2-3-3.1", "gen_vectors": [[2, 1, 4, 3, 6, 5, 8, 7, 10, 9, 12, 11], [4, 3, 2, 1, 8, 7, 6, 5, 12, 11, 10, 9], [3, 4, 1, 2, 7, 8, 5, 6, 11, 12, 9, 10], [4, 3, 2, 1, 8, 7, 6, 5, 12, 11, 10, 9], [3, 4, 1, 2, 7, 8, 5, 6, 11, 12, 9, 10], [5, 8, 6, 7, 9, 12, 10, 11, 1, 4, 2, 3], [10, 12, 11, 9, 2, 4, 3, 1, 6, 8, 7, 5]], "total_label": "12.12-3.0.2-2-2-2-2-3-3.1.51", "cc": [1, 51], "label": "12.12-3.0.2-2-2-2-2-3-3", "genus": 12, "signature": "[0,2,2,2,2,2,3,3]", "group": "[12,3]", "_id": {"$oid": "59515d6e3fce4a6697d4dde4"}}, {"passport_label": "12.12-3.0.2-2-2-2-2-3-3.1", "gen_vectors": [[2, 1, 4, 3, 6, 5, 8, 7, 10, 9, 12, 11], [4, 3, 2, 1, 8, 7, 6, 5, 12, 11, 10, 9], [3, 4, 1, 2, 7, 8, 5, 6, 11, 12, 9, 10], [3, 4, 1, 2, 7, 8, 5, 6, 11, 12, 9, 10], [2, 1, 4, 3, 6, 5, 8, 7, 10, 9, 12, 11], [5, 8, 6, 7, 9, 12, 10, 11, 1, 4, 2, 3], [12, 10, 9, 11, 4, 2, 1, 3, 8, 6, 5, 7]], "total_label": "12.12-3.0.2-2-2-2-2-3-3.1.52", "cc": [1, 52], "label": "12.12-3.0.2-2-2-2-2-3-3", "genus": 12, "signature": "[0,2,2,2,2,2,3,3]", "group": "[12,3]", "_id": {"$oid": "59515d6f3fce4a6697d4dde5"}}, {"passport_label": "12.12-3.0.2-2-2-2-2-3-3.1", "gen_vectors": [[2, 1, 4, 3, 6, 5, 8, 7, 10, 9, 12, 11], [4, 3, 2, 1, 8, 7, 6, 5, 12, 11, 10, 9], [3, 4, 1, 2, 7, 8, 5, 6, 11, 12, 9, 10], [3, 4, 1, 2, 7, 8, 5, 6, 11, 12, 9, 10], [4, 3, 2, 1, 8, 7, 6, 5, 12, 11, 10, 9], [5, 8, 6, 7, 9, 12, 10, 11, 1, 4, 2, 3], [10, 12, 11, 9, 2, 4, 3, 1, 6, 8, 7, 5]], "total_label": "12.12-3.0.2-2-2-2-2-3-3.1.53", "cc": [1, 53], "label": "12.12-3.0.2-2-2-2-2-3-3", "genus": 12, "signature": "[0,2,2,2,2,2,3,3]", "group": "[12,3]", "_id": {"$oid": "59515d703fce4a6697d4dde6"}}, {"passport_label": "12.12-3.0.2-2-2-2-2-3-3.1", "gen_vectors": [[2, 1, 4, 3, 6, 5, 8, 7, 10, 9, 12, 11], [4, 3, 2, 1, 8, 7, 6, 5, 12, 11, 10, 9], [3, 4, 1, 2, 7, 8, 5, 6, 11, 12, 9, 10], [3, 4, 1, 2, 7, 8, 5, 6, 11, 12, 9, 10], [3, 4, 1, 2, 7, 8, 5, 6, 11, 12, 9, 10], [5, 8, 6, 7, 9, 12, 10, 11, 1, 4, 2, 3], [9, 11, 12, 10, 1, 3, 4, 2, 5, 7, 8, 6]], "total_label": "12.12-3.0.2-2-2-2-2-3-3.1.54", "cc": [1, 54], "label": "12.12-3.0.2-2-2-2-2-3-3", "genus": 12, "signature": "[0,2,2,2,2,2,3,3]", "group": "[12,3]", "_id": {"$oid": "59515d703fce4a6697d4dde7"}}, {"passport_label": "12.12-3.0.2-2-2-2-2-3-3.1", "gen_vectors": [[2, 1, 4, 3, 6, 5, 8, 7, 10, 9, 12, 11], [3, 4, 1, 2, 7, 8, 5, 6, 11, 12, 9, 10], [2, 1, 4, 3, 6, 5, 8, 7, 10, 9, 12, 11], [2, 1, 4, 3, 6, 5, 8, 7, 10, 9, 12, 11], [2, 1, 4, 3, 6, 5, 8, 7, 10, 9, 12, 11], [5, 8, 6, 7, 9, 12, 10, 11, 1, 4, 2, 3], [11, 9, 10, 12, 3, 1, 2, 4, 7, 5, 6, 8]], "total_label": "12.12-3.0.2-2-2-2-2-3-3.1.55", "cc": [1, 55], "label": "12.12-3.0.2-2-2-2-2-3-3", "genus": 12, "signature": "[0,2,2,2,2,2,3,3]", "group": "[12,3]", "_id": {"$oid": "59515d713fce4a6697d4dde8"}}, {"passport_label": "12.12-3.0.2-2-2-2-2-3-3.1", "gen_vectors": [[2, 1, 4, 3, 6, 5, 8, 7, 10, 9, 12, 11], [3, 4, 1, 2, 7, 8, 5, 6, 11, 12, 9, 10], [2, 1, 4, 3, 6, 5, 8, 7, 10, 9, 12, 11], [2, 1, 4, 3, 6, 5, 8, 7, 10, 9, 12, 11], [4, 3, 2, 1, 8, 7, 6, 5, 12, 11, 10, 9], [5, 8, 6, 7, 9, 12, 10, 11, 1, 4, 2, 3], [9, 11, 12, 10, 1, 3, 4, 2, 5, 7, 8, 6]], "total_label": "12.12-3.0.2-2-2-2-2-3-3.1.56", "cc": [1, 56], "label": "12.12-3.0.2-2-2-2-2-3-3", "genus": 12, "signature": "[0,2,2,2,2,2,3,3]", "group": "[12,3]", "_id": {"$oid": "59515d713fce4a6697d4dde9"}}, {"passport_label": "12.12-3.0.2-2-2-2-2-3-3.1", "gen_vectors": [[2, 1, 4, 3, 6, 5, 8, 7, 10, 9, 12, 11], [3, 4, 1, 2, 7, 8, 5, 6, 11, 12, 9, 10], [2, 1, 4, 3, 6, 5, 8, 7, 10, 9, 12, 11], [2, 1, 4, 3, 6, 5, 8, 7, 10, 9, 12, 11], [3, 4, 1, 2, 7, 8, 5, 6, 11, 12, 9, 10], [5, 8, 6, 7, 9, 12, 10, 11, 1, 4, 2, 3], [10, 12, 11, 9, 2, 4, 3, 1, 6, 8, 7, 5]], "total_label": "12.12-3.0.2-2-2-2-2-3-3.1.57", "cc": [1, 57], "label": "12.12-3.0.2-2-2-2-2-3-3", "genus": 12, "signature": "[0,2,2,2,2,2,3,3]", "group": "[12,3]", "_id": {"$oid": "59515d713fce4a6697d4ddea"}}, {"passport_label": "12.12-3.0.2-2-2-2-2-3-3.1", "gen_vectors": [[2, 1, 4, 3, 6, 5, 8, 7, 10, 9, 12, 11], [3, 4, 1, 2, 7, 8, 5, 6, 11, 12, 9, 10], [2, 1, 4, 3, 6, 5, 8, 7, 10, 9, 12, 11], [4, 3, 2, 1, 8, 7, 6, 5, 12, 11, 10, 9], [2, 1, 4, 3, 6, 5, 8, 7, 10, 9, 12, 11], [5, 8, 6, 7, 9, 12, 10, 11, 1, 4, 2, 3], [9, 11, 12, 10, 1, 3, 4, 2, 5, 7, 8, 6]], "total_label": "12.12-3.0.2-2-2-2-2-3-3.1.58", "cc": [1, 58], "label": "12.12-3.0.2-2-2-2-2-3-3", "genus": 12, "signature": "[0,2,2,2,2,2,3,3]", "group": "[12,3]", "_id": {"$oid": "59515d723fce4a6697d4ddeb"}}, {"passport_label": "12.12-3.0.2-2-2-2-2-3-3.1", "gen_vectors": [[2, 1, 4, 3, 6, 5, 8, 7, 10, 9, 12, 11], [3, 4, 1, 2, 7, 8, 5, 6, 11, 12, 9, 10], [2, 1, 4, 3, 6, 5, 8, 7, 10, 9, 12, 11], [4, 3, 2, 1, 8, 7, 6, 5, 12, 11, 10, 9], [4, 3, 2, 1, 8, 7, 6, 5, 12, 11, 10, 9], [5, 8, 6, 7, 9, 12, 10, 11, 1, 4, 2, 3], [11, 9, 10, 12, 3, 1, 2, 4, 7, 5, 6, 8]], "total_label": "12.12-3.0.2-2-2-2-2-3-3.1.59", "cc": [1, 59], "label": "12.12-3.0.2-2-2-2-2-3-3", "genus": 12, "signature": "[0,2,2,2,2,2,3,3]", "group": "[12,3]", "_id": {"$oid": "59515d723fce4a6697d4ddec"}}, {"passport_label": "12.12-3.0.2-2-2-2-2-3-3.1", "gen_vectors": [[2, 1, 4, 3, 6, 5, 8, 7, 10, 9, 12, 11], [3, 4, 1, 2, 7, 8, 5, 6, 11, 12, 9, 10], [2, 1, 4, 3, 6, 5, 8, 7, 10, 9, 12, 11], [4, 3, 2, 1, 8, 7, 6, 5, 12, 11, 10, 9], [3, 4, 1, 2, 7, 8, 5, 6, 11, 12, 9, 10], [5, 8, 6, 7, 9, 12, 10, 11, 1, 4, 2, 3], [12, 10, 9, 11, 4, 2, 1, 3, 8, 6, 5, 7]], "total_label": "12.12-3.0.2-2-2-2-2-3-3.1.60", "cc": [1, 60], "label": "12.12-3.0.2-2-2-2-2-3-3", "genus": 12, "signature": "[0,2,2,2,2,2,3,3]", "group": "[12,3]", "_id": {"$oid": "59515d733fce4a6697d4dded"}}, {"passport_label": "12.12-3.0.2-2-2-2-2-3-3.1", "gen_vectors": [[2, 1, 4, 3, 6, 5, 8, 7, 10, 9, 12, 11], [3, 4, 1, 2, 7, 8, 5, 6, 11, 12, 9, 10], [2, 1, 4, 3, 6, 5, 8, 7, 10, 9, 12, 11], [3, 4, 1, 2, 7, 8, 5, 6, 11, 12, 9, 10], [2, 1, 4, 3, 6, 5, 8, 7, 10, 9, 12, 11], [5, 8, 6, 7, 9, 12, 10, 11, 1, 4, 2, 3], [10, 12, 11, 9, 2, 4, 3, 1, 6, 8, 7, 5]], "total_label": "12.12-3.0.2-2-2-2-2-3-3.1.61", "cc": [1, 61], "label": "12.12-3.0.2-2-2-2-2-3-3", "genus": 12, "signature": "[0,2,2,2,2,2,3,3]", "group": "[12,3]", "_id": {"$oid": "59515d743fce4a6697d4ddee"}}, {"passport_label": "12.12-3.0.2-2-2-2-2-3-3.1", "gen_vectors": [[2, 1, 4, 3, 6, 5, 8, 7, 10, 9, 12, 11], [3, 4, 1, 2, 7, 8, 5, 6, 11, 12, 9, 10], [2, 1, 4, 3, 6, 5, 8, 7, 10, 9, 12, 11], [3, 4, 1, 2, 7, 8, 5, 6, 11, 12, 9, 10], [4, 3, 2, 1, 8, 7, 6, 5, 12, 11, 10, 9], [5, 8, 6, 7, 9, 12, 10, 11, 1, 4, 2, 3], [12, 10, 9, 11, 4, 2, 1, 3, 8, 6, 5, 7]], "total_label": "12.12-3.0.2-2-2-2-2-3-3.1.62", "cc": [1, 62], "label": "12.12-3.0.2-2-2-2-2-3-3", "genus": 12, "signature": "[0,2,2,2,2,2,3,3]", "group": "[12,3]", "_id": {"$oid": "59515d743fce4a6697d4ddef"}}, {"passport_label": "12.12-3.0.2-2-2-2-2-3-3.1", "gen_vectors": [[2, 1, 4, 3, 6, 5, 8, 7, 10, 9, 12, 11], [3, 4, 1, 2, 7, 8, 5, 6, 11, 12, 9, 10], [2, 1, 4, 3, 6, 5, 8, 7, 10, 9, 12, 11], [3, 4, 1, 2, 7, 8, 5, 6, 11, 12, 9, 10], [3, 4, 1, 2, 7, 8, 5, 6, 11, 12, 9, 10], [5, 8, 6, 7, 9, 12, 10, 11, 1, 4, 2, 3], [11, 9, 10, 12, 3, 1, 2, 4, 7, 5, 6, 8]], "total_label": "12.12-3.0.2-2-2-2-2-3-3.1.63", "cc": [1, 63], "label": "12.12-3.0.2-2-2-2-2-3-3", "genus": 12, "signature": "[0,2,2,2,2,2,3,3]", "group": "[12,3]", "_id": {"$oid": "59515d753fce4a6697d4ddf0"}}, {"passport_label": "12.12-3.0.2-2-2-2-2-3-3.1", "gen_vectors": [[2, 1, 4, 3, 6, 5, 8, 7, 10, 9, 12, 11], [3, 4, 1, 2, 7, 8, 5, 6, 11, 12, 9, 10], [4, 3, 2, 1, 8, 7, 6, 5, 12, 11, 10, 9], [2, 1, 4, 3, 6, 5, 8, 7, 10, 9, 12, 11], [2, 1, 4, 3, 6, 5, 8, 7, 10, 9, 12, 11], [5, 8, 6, 7, 9, 12, 10, 11, 1, 4, 2, 3], [9, 11, 12, 10, 1, 3, 4, 2, 5, 7, 8, 6]], "total_label": "12.12-3.0.2-2-2-2-2-3-3.1.64", "cc": [1, 64], "label": "12.12-3.0.2-2-2-2-2-3-3", "genus": 12, "signature": "[0,2,2,2,2,2,3,3]", "group": "[12,3]", "_id": {"$oid": "59515d753fce4a6697d4ddf1"}}, {"passport_label": "12.12-3.0.2-2-2-2-2-3-3.1", "gen_vectors": [[2, 1, 4, 3, 6, 5, 8, 7, 10, 9, 12, 11], [3, 4, 1, 2, 7, 8, 5, 6, 11, 12, 9, 10], [4, 3, 2, 1, 8, 7, 6, 5, 12, 11, 10, 9], [2, 1, 4, 3, 6, 5, 8, 7, 10, 9, 12, 11], [4, 3, 2, 1, 8, 7, 6, 5, 12, 11, 10, 9], [5, 8, 6, 7, 9, 12, 10, 11, 1, 4, 2, 3], [11, 9, 10, 12, 3, 1, 2, 4, 7, 5, 6, 8]], "total_label": "12.12-3.0.2-2-2-2-2-3-3.1.65", "cc": [1, 65], "label": "12.12-3.0.2-2-2-2-2-3-3", "genus": 12, "signature": "[0,2,2,2,2,2,3,3]", "group": "[12,3]", "_id": {"$oid": "59515d763fce4a6697d4ddf2"}}, {"passport_label": "12.12-3.0.2-2-2-2-2-3-3.1", "gen_vectors": [[2, 1, 4, 3, 6, 5, 8, 7, 10, 9, 12, 11], [3, 4, 1, 2, 7, 8, 5, 6, 11, 12, 9, 10], [4, 3, 2, 1, 8, 7, 6, 5, 12, 11, 10, 9], [2, 1, 4, 3, 6, 5, 8, 7, 10, 9, 12, 11], [3, 4, 1, 2, 7, 8, 5, 6, 11, 12, 9, 10], [5, 8, 6, 7, 9, 12, 10, 11, 1, 4, 2, 3], [12, 10, 9, 11, 4, 2, 1, 3, 8, 6, 5, 7]], "total_label": "12.12-3.0.2-2-2-2-2-3-3.1.66", "cc": [1, 66], "label": "12.12-3.0.2-2-2-2-2-3-3", "genus": 12, "signature": "[0,2,2,2,2,2,3,3]", "group": "[12,3]", "_id": {"$oid": "59515d763fce4a6697d4ddf3"}}, {"passport_label": "12.12-3.0.2-2-2-2-2-3-3.1", "gen_vectors": [[2, 1, 4, 3, 6, 5, 8, 7, 10, 9, 12, 11], [3, 4, 1, 2, 7, 8, 5, 6, 11, 12, 9, 10], [4, 3, 2, 1, 8, 7, 6, 5, 12, 11, 10, 9], [4, 3, 2, 1, 8, 7, 6, 5, 12, 11, 10, 9], [2, 1, 4, 3, 6, 5, 8, 7, 10, 9, 12, 11], [5, 8, 6, 7, 9, 12, 10, 11, 1, 4, 2, 3], [11, 9, 10, 12, 3, 1, 2, 4, 7, 5, 6, 8]], "total_label": "12.12-3.0.2-2-2-2-2-3-3.1.67", "cc": [1, 67], "label": "12.12-3.0.2-2-2-2-2-3-3", "genus": 12, "signature": "[0,2,2,2,2,2,3,3]", "group": "[12,3]", "_id": {"$oid": "59515d773fce4a6697d4ddf4"}}, {"passport_label": "12.12-3.0.2-2-2-2-2-3-3.1", "gen_vectors": [[2, 1, 4, 3, 6, 5, 8, 7, 10, 9, 12, 11], [3, 4, 1, 2, 7, 8, 5, 6, 11, 12, 9, 10], [4, 3, 2, 1, 8, 7, 6, 5, 12, 11, 10, 9], [4, 3, 2, 1, 8, 7, 6, 5, 12, 11, 10, 9], [4, 3, 2, 1, 8, 7, 6, 5, 12, 11, 10, 9], [5, 8, 6, 7, 9, 12, 10, 11, 1, 4, 2, 3], [9, 11, 12, 10, 1, 3, 4, 2, 5, 7, 8, 6]], "total_label": "12.12-3.0.2-2-2-2-2-3-3.1.68", "cc": [1, 68], "label": "12.12-3.0.2-2-2-2-2-3-3", "genus": 12, "signature": "[0,2,2,2,2,2,3,3]", "group": "[12,3]", "_id": {"$oid": "59515d773fce4a6697d4ddf5"}}, {"passport_label": "12.12-3.0.2-2-2-2-2-3-3.1", "gen_vectors": [[2, 1, 4, 3, 6, 5, 8, 7, 10, 9, 12, 11], [3, 4, 1, 2, 7, 8, 5, 6, 11, 12, 9, 10], [4, 3, 2, 1, 8, 7, 6, 5, 12, 11, 10, 9], [4, 3, 2, 1, 8, 7, 6, 5, 12, 11, 10, 9], [3, 4, 1, 2, 7, 8, 5, 6, 11, 12, 9, 10], [5, 8, 6, 7, 9, 12, 10, 11, 1, 4, 2, 3], [10, 12, 11, 9, 2, 4, 3, 1, 6, 8, 7, 5]], "total_label": "12.12-3.0.2-2-2-2-2-3-3.1.69", "cc": [1, 69], "label": "12.12-3.0.2-2-2-2-2-3-3", "genus": 12, "signature": "[0,2,2,2,2,2,3,3]", "group": "[12,3]", "_id": {"$oid": "59515d773fce4a6697d4ddf6"}}, {"passport_label": "12.12-3.0.2-2-2-2-2-3-3.1", "gen_vectors": [[2, 1, 4, 3, 6, 5, 8, 7, 10, 9, 12, 11], [3, 4, 1, 2, 7, 8, 5, 6, 11, 12, 9, 10], [4, 3, 2, 1, 8, 7, 6, 5, 12, 11, 10, 9], [3, 4, 1, 2, 7, 8, 5, 6, 11, 12, 9, 10], [2, 1, 4, 3, 6, 5, 8, 7, 10, 9, 12, 11], [5, 8, 6, 7, 9, 12, 10, 11, 1, 4, 2, 3], [12, 10, 9, 11, 4, 2, 1, 3, 8, 6, 5, 7]], "total_label": "12.12-3.0.2-2-2-2-2-3-3.1.70", "cc": [1, 70], "label": "12.12-3.0.2-2-2-2-2-3-3", "genus": 12, "signature": "[0,2,2,2,2,2,3,3]", "group": "[12,3]", "_id": {"$oid": "59515d783fce4a6697d4ddf7"}}, {"passport_label": "12.12-3.0.2-2-2-2-2-3-3.1", "gen_vectors": [[2, 1, 4, 3, 6, 5, 8, 7, 10, 9, 12, 11], [3, 4, 1, 2, 7, 8, 5, 6, 11, 12, 9, 10], [4, 3, 2, 1, 8, 7, 6, 5, 12, 11, 10, 9], [3, 4, 1, 2, 7, 8, 5, 6, 11, 12, 9, 10], [4, 3, 2, 1, 8, 7, 6, 5, 12, 11, 10, 9], [5, 8, 6, 7, 9, 12, 10, 11, 1, 4, 2, 3], [10, 12, 11, 9, 2, 4, 3, 1, 6, 8, 7, 5]], "total_label": "12.12-3.0.2-2-2-2-2-3-3.1.71", "cc": [1, 71], "label": "12.12-3.0.2-2-2-2-2-3-3", "genus": 12, "signature": "[0,2,2,2,2,2,3,3]", "group": "[12,3]", "_id": {"$oid": "59515d783fce4a6697d4ddf8"}}, {"passport_label": "12.12-3.0.2-2-2-2-2-3-3.1", "gen_vectors": [[2, 1, 4, 3, 6, 5, 8, 7, 10, 9, 12, 11], [3, 4, 1, 2, 7, 8, 5, 6, 11, 12, 9, 10], [4, 3, 2, 1, 8, 7, 6, 5, 12, 11, 10, 9], [3, 4, 1, 2, 7, 8, 5, 6, 11, 12, 9, 10], [3, 4, 1, 2, 7, 8, 5, 6, 11, 12, 9, 10], [5, 8, 6, 7, 9, 12, 10, 11, 1, 4, 2, 3], [9, 11, 12, 10, 1, 3, 4, 2, 5, 7, 8, 6]], "total_label": "12.12-3.0.2-2-2-2-2-3-3.1.72", "cc": [1, 72], "label": "12.12-3.0.2-2-2-2-2-3-3", "genus": 12, "signature": "[0,2,2,2,2,2,3,3]", "group": "[12,3]", "_id": {"$oid": "59515d793fce4a6697d4ddf9"}}, {"passport_label": "12.12-3.0.2-2-2-2-2-3-3.1", "gen_vectors": [[2, 1, 4, 3, 6, 5, 8, 7, 10, 9, 12, 11], [3, 4, 1, 2, 7, 8, 5, 6, 11, 12, 9, 10], [3, 4, 1, 2, 7, 8, 5, 6, 11, 12, 9, 10], [2, 1, 4, 3, 6, 5, 8, 7, 10, 9, 12, 11], [2, 1, 4, 3, 6, 5, 8, 7, 10, 9, 12, 11], [5, 8, 6, 7, 9, 12, 10, 11, 1, 4, 2, 3], [10, 12, 11, 9, 2, 4, 3, 1, 6, 8, 7, 5]], "total_label": "12.12-3.0.2-2-2-2-2-3-3.1.73", "cc": [1, 73], "label": "12.12-3.0.2-2-2-2-2-3-3", "genus": 12, "signature": "[0,2,2,2,2,2,3,3]", "group": "[12,3]", "_id": {"$oid": "59515d793fce4a6697d4ddfa"}}, {"passport_label": "12.12-3.0.2-2-2-2-2-3-3.1", "gen_vectors": [[2, 1, 4, 3, 6, 5, 8, 7, 10, 9, 12, 11], [3, 4, 1, 2, 7, 8, 5, 6, 11, 12, 9, 10], [3, 4, 1, 2, 7, 8, 5, 6, 11, 12, 9, 10], [2, 1, 4, 3, 6, 5, 8, 7, 10, 9, 12, 11], [4, 3, 2, 1, 8, 7, 6, 5, 12, 11, 10, 9], [5, 8, 6, 7, 9, 12, 10, 11, 1, 4, 2, 3], [12, 10, 9, 11, 4, 2, 1, 3, 8, 6, 5, 7]], "total_label": "12.12-3.0.2-2-2-2-2-3-3.1.74", "cc": [1, 74], "label": "12.12-3.0.2-2-2-2-2-3-3", "genus": 12, "signature": "[0,2,2,2,2,2,3,3]", "group": "[12,3]", "_id": {"$oid": "59515d7a3fce4a6697d4ddfb"}}, {"passport_label": "12.12-3.0.2-2-2-2-2-3-3.1", "gen_vectors": [[2, 1, 4, 3, 6, 5, 8, 7, 10, 9, 12, 11], [3, 4, 1, 2, 7, 8, 5, 6, 11, 12, 9, 10], [3, 4, 1, 2, 7, 8, 5, 6, 11, 12, 9, 10], [2, 1, 4, 3, 6, 5, 8, 7, 10, 9, 12, 11], [3, 4, 1, 2, 7, 8, 5, 6, 11, 12, 9, 10], [5, 8, 6, 7, 9, 12, 10, 11, 1, 4, 2, 3], [11, 9, 10, 12, 3, 1, 2, 4, 7, 5, 6, 8]], "total_label": "12.12-3.0.2-2-2-2-2-3-3.1.75", "cc": [1, 75], "label": "12.12-3.0.2-2-2-2-2-3-3", "genus": 12, "signature": "[0,2,2,2,2,2,3,3]", "group": "[12,3]", "_id": {"$oid": "59515d7a3fce4a6697d4ddfc"}}, {"passport_label": "12.12-3.0.2-2-2-2-2-3-3.1", "gen_vectors": [[2, 1, 4, 3, 6, 5, 8, 7, 10, 9, 12, 11], [3, 4, 1, 2, 7, 8, 5, 6, 11, 12, 9, 10], [3, 4, 1, 2, 7, 8, 5, 6, 11, 12, 9, 10], [4, 3, 2, 1, 8, 7, 6, 5, 12, 11, 10, 9], [2, 1, 4, 3, 6, 5, 8, 7, 10, 9, 12, 11], [5, 8, 6, 7, 9, 12, 10, 11, 1, 4, 2, 3], [12, 10, 9, 11, 4, 2, 1, 3, 8, 6, 5, 7]], "total_label": "12.12-3.0.2-2-2-2-2-3-3.1.76", "cc": [1, 76], "label": "12.12-3.0.2-2-2-2-2-3-3", "genus": 12, "signature": "[0,2,2,2,2,2,3,3]", "group": "[12,3]", "_id": {"$oid": "59515d7b3fce4a6697d4ddfd"}}, {"passport_label": "12.12-3.0.2-2-2-2-2-3-3.1", "gen_vectors": [[2, 1, 4, 3, 6, 5, 8, 7, 10, 9, 12, 11], [3, 4, 1, 2, 7, 8, 5, 6, 11, 12, 9, 10], [3, 4, 1, 2, 7, 8, 5, 6, 11, 12, 9, 10], [4, 3, 2, 1, 8, 7, 6, 5, 12, 11, 10, 9], [4, 3, 2, 1, 8, 7, 6, 5, 12, 11, 10, 9], [5, 8, 6, 7, 9, 12, 10, 11, 1, 4, 2, 3], [10, 12, 11, 9, 2, 4, 3, 1, 6, 8, 7, 5]], "total_label": "12.12-3.0.2-2-2-2-2-3-3.1.77", "cc": [1, 77], "label": "12.12-3.0.2-2-2-2-2-3-3", "genus": 12, "signature": "[0,2,2,2,2,2,3,3]", "group": "[12,3]", "_id": {"$oid": "59515d7b3fce4a6697d4ddfe"}}, {"passport_label": "12.12-3.0.2-2-2-2-2-3-3.1", "gen_vectors": [[2, 1, 4, 3, 6, 5, 8, 7, 10, 9, 12, 11], [3, 4, 1, 2, 7, 8, 5, 6, 11, 12, 9, 10], [3, 4, 1, 2, 7, 8, 5, 6, 11, 12, 9, 10], [4, 3, 2, 1, 8, 7, 6, 5, 12, 11, 10, 9], [3, 4, 1, 2, 7, 8, 5, 6, 11, 12, 9, 10], [5, 8, 6, 7, 9, 12, 10, 11, 1, 4, 2, 3], [9, 11, 12, 10, 1, 3, 4, 2, 5, 7, 8, 6]], "total_label": "12.12-3.0.2-2-2-2-2-3-3.1.78", "cc": [1, 78], "label": "12.12-3.0.2-2-2-2-2-3-3", "genus": 12, "signature": "[0,2,2,2,2,2,3,3]", "group": "[12,3]", "_id": {"$oid": "59515d7c3fce4a6697d4ddff"}}, {"passport_label": "12.12-3.0.2-2-2-2-2-3-3.1", "gen_vectors": [[2, 1, 4, 3, 6, 5, 8, 7, 10, 9, 12, 11], [3, 4, 1, 2, 7, 8, 5, 6, 11, 12, 9, 10], [3, 4, 1, 2, 7, 8, 5, 6, 11, 12, 9, 10], [3, 4, 1, 2, 7, 8, 5, 6, 11, 12, 9, 10], [2, 1, 4, 3, 6, 5, 8, 7, 10, 9, 12, 11], [5, 8, 6, 7, 9, 12, 10, 11, 1, 4, 2, 3], [11, 9, 10, 12, 3, 1, 2, 4, 7, 5, 6, 8]], "total_label": "12.12-3.0.2-2-2-2-2-3-3.1.79", "cc": [1, 79], "label": "12.12-3.0.2-2-2-2-2-3-3", "genus": 12, "signature": "[0,2,2,2,2,2,3,3]", "group": "[12,3]", "_id": {"$oid": "59515d7d3fce4a6697d4de00"}}, {"passport_label": "12.12-3.0.2-2-2-2-2-3-3.1", "gen_vectors": [[2, 1, 4, 3, 6, 5, 8, 7, 10, 9, 12, 11], [3, 4, 1, 2, 7, 8, 5, 6, 11, 12, 9, 10], [3, 4, 1, 2, 7, 8, 5, 6, 11, 12, 9, 10], [3, 4, 1, 2, 7, 8, 5, 6, 11, 12, 9, 10], [4, 3, 2, 1, 8, 7, 6, 5, 12, 11, 10, 9], [5, 8, 6, 7, 9, 12, 10, 11, 1, 4, 2, 3], [9, 11, 12, 10, 1, 3, 4, 2, 5, 7, 8, 6]], "total_label": "12.12-3.0.2-2-2-2-2-3-3.1.80", "cc": [1, 80], "label": "12.12-3.0.2-2-2-2-2-3-3", "genus": 12, "signature": "[0,2,2,2,2,2,3,3]", "group": "[12,3]", "_id": {"$oid": "59515d7d3fce4a6697d4de01"}}, {"passport_label": "12.12-3.0.2-2-2-2-2-3-3.1", "gen_vectors": [[2, 1, 4, 3, 6, 5, 8, 7, 10, 9, 12, 11], [3, 4, 1, 2, 7, 8, 5, 6, 11, 12, 9, 10], [3, 4, 1, 2, 7, 8, 5, 6, 11, 12, 9, 10], [3, 4, 1, 2, 7, 8, 5, 6, 11, 12, 9, 10], [3, 4, 1, 2, 7, 8, 5, 6, 11, 12, 9, 10], [5, 8, 6, 7, 9, 12, 10, 11, 1, 4, 2, 3], [10, 12, 11, 9, 2, 4, 3, 1, 6, 8, 7, 5]], "total_label": "12.12-3.0.2-2-2-2-2-3-3.1.81", "cc": [1, 81], "label": "12.12-3.0.2-2-2-2-2-3-3", "genus": 12, "signature": "[0,2,2,2,2,2,3,3]", "group": "[12,3]", "_id": {"$oid": "59515d7e3fce4a6697d4de02"}}]
[{"passport_label": "12.12-4.0.2-2-2-2-2-3-3.1", "gen_vectors": [[4, 5, 6, 1, 2, 3, 10, 11, 12, 7, 8, 9], [4, 5, 6, 1, 2, 3, 10, 11, 12, 7, 8, 9], [4, 5, 6, 1, 2, 3, 10, 11, 12, 7, 8, 9], [7, 9, 8, 10, 12, 11, 1, 3, 2, 4, 6, 5], [10, 12, 11, 7, 9, 8, 4, 6, 5, 1, 3, 2], [2, 3, 1, 5, 6, 4, 8, 9, 7, 11, 12, 10], [3, 1, 2, 6, 4, 5, 9, 7, 8, 12, 10, 11]], "total_label": "12.12-4.0.2-2-2-2-2-3-3.1.1", "cc": [1, 1], "label": "12.12-4.0.2-2-2-2-2-3-3", "genus": 12, "signature": "[0,2,2,2,2,2,3,3]", "group": "[12,4]", "_id": {"$oid": "59515d7f3fce4a6697d4de03"}}, {"passport_label": "12.12-4.0.2-2-2-2-2-3-3.1", "gen_vectors": [[4, 5, 6, 1, 2, 3, 10, 11, 12, 7, 8, 9], [4, 5, 6, 1, 2, 3, 10, 11, 12, 7, 8, 9], [4, 5, 6, 1, 2, 3, 10, 11, 12, 7, 8, 9], [7, 9, 8, 10, 12, 11, 1, 3, 2, 4, 6, 5], [12, 11, 10, 9, 8, 7, 6, 5, 4, 3, 2, 1], [3, 1, 2, 6, 4, 5, 9, 7, 8, 12, 10, 11], [3, 1, 2, 6, 4, 5, 9, 7, 8, 12, 10, 11]], "total_label": "12.12-4.0.2-2-2-2-2-3-3.1.2", "cc": [1, 2], "label": "12.12-4.0.2-2-2-2-2-3-3", "genus": 12, "signature": "[0,2,2,2,2,2,3,3]", "group": "[12,4]", "_id": {"$oid": "59515d7f3fce4a6697d4de04"}}, {"passport_label": "12.12-4.0.2-2-2-2-2-3-3.2", "gen_vectors": [[4, 5, 6, 1, 2, 3, 10, 11, 12, 7, 8, 9], [7, 9, 8, 10, 12, 11, 1, 3, 2, 4, 6, 5], [7, 9, 8, 10, 12, 11, 1, 3, 2, 4, 6, 5], [7, 9, 8, 10, 12, 11, 1, 3, 2, 4, 6, 5], [10, 12, 11, 7, 9, 8, 4, 6, 5, 1, 3, 2], [2, 3, 1, 5, 6, 4, 8, 9, 7, 11, 12, 10], [3, 1, 2, 6, 4, 5, 9, 7, 8, 12, 10, 11]], "total_label": "12.12-4.0.2-2-2-2-2-3-3.2.1", "cc": [2, 1], "label": "12.12-4.0.2-2-2-2-2-3-3", "genus": 12, "signature": "[0,2,2,2,2,2,3,3]", "group": "[12,4]", "_id": {"$oid": "59515d803fce4a6697d4de05"}}, {"passport_label": "12.12-4.0.2-2-2-2-2-3-3.2", "gen_vectors": [[4, 5, 6, 1, 2, 3, 10, 11, 12, 7, 8, 9], [7, 9, 8, 10, 12, 11, 1, 3, 2, 4, 6, 5], [7, 9, 8, 10, 12, 11, 1, 3, 2, 4, 6, 5], [7, 9, 8, 10, 12, 11, 1, 3, 2, 4, 6, 5], [12, 11, 10, 9, 8, 7, 6, 5, 4, 3, 2, 1], [3, 1, 2, 6, 4, 5, 9, 7, 8, 12, 10, 11], [3, 1, 2, 6, 4, 5, 9, 7, 8, 12, 10, 11]], "total_label": "12.12-4.0.2-2-2-2-2-3-3.2.2", "cc": [2, 2], "label": "12.12-4.0.2-2-2-2-2-3-3", "genus": 12, "signature": "[0,2,2,2,2,2,3,3]", "group": "[12,4]", "_id": {"$oid": "59515d803fce4a6697d4de06"}}, {"passport_label": "12.12-4.0.2-2-2-2-2-3-3.2", "gen_vectors": [[4, 5, 6, 1, 2, 3, 10, 11, 12, 7, 8, 9], [7, 9, 8, 10, 12, 11, 1, 3, 2, 4, 6, 5], [7, 9, 8, 10, 12, 11, 1, 3, 2, 4, 6, 5], [9, 8, 7, 12, 11, 10, 3, 2, 1, 6, 5, 4], [10, 12, 11, 7, 9, 8, 4, 6, 5, 1, 3, 2], [2, 3, 1, 5, 6, 4, 8, 9, 7, 11, 12, 10], [2, 3, 1, 5, 6, 4, 8, 9, 7, 11, 12, 10]], "total_label": "12.12-4.0.2-2-2-2-2-3-3.2.3", "cc": [2, 3], "label": "12.12-4.0.2-2-2-2-2-3-3", "genus": 12, "signature": "[0,2,2,2,2,2,3,3]", "group": "[12,4]", "_id": {"$oid": "59515d803fce4a6697d4de07"}}, {"passport_label": "12.12-4.0.2-2-2-2-2-3-3.2", "gen_vectors": [[4, 5, 6, 1, 2, 3, 10, 11, 12, 7, 8, 9], [7, 9, 8, 10, 12, 11, 1, 3, 2, 4, 6, 5], [7, 9, 8, 10, 12, 11, 1, 3, 2, 4, 6, 5], [9, 8, 7, 12, 11, 10, 3, 2, 1, 6, 5, 4], [12, 11, 10, 9, 8, 7, 6, 5, 4, 3, 2, 1], [2, 3, 1, 5, 6, 4, 8, 9, 7, 11, 12, 10], [3, 1, 2, 6, 4, 5, 9, 7, 8, 12, 10, 11]], "total_label": "12.12-4.0.2-2-2-2-2-3-3.2.4", "cc": [2, 4], "label": "12.12-4.0.2-2-2-2-2-3-3", "genus": 12, "signature": "[0,2,2,2,2,2,3,3]", "group": "[12,4]", "_id": {"$oid": "59515d813fce4a6697d4de08"}}, {"passport_label": "12.12-4.0.2-2-2-2-2-3-3.2", "gen_vectors": [[4, 5, 6, 1, 2, 3, 10, 11, 12, 7, 8, 9], [7, 9, 8, 10, 12, 11, 1, 3, 2, 4, 6, 5], [7, 9, 8, 10, 12, 11, 1, 3, 2, 4, 6, 5], [9, 8, 7, 12, 11, 10, 3, 2, 1, 6, 5, 4], [12, 11, 10, 9, 8, 7, 6, 5, 4, 3, 2, 1], [3, 1, 2, 6, 4, 5, 9, 7, 8, 12, 10, 11], [2, 3, 1, 5, 6, 4, 8, 9, 7, 11, 12, 10]], "total_label": "12.12-4.0.2-2-2-2-2-3-3.2.5", "cc": [2, 5], "label": "12.12-4.0.2-2-2-2-2-3-3", "genus": 12, "signature": "[0,2,2,2,2,2,3,3]", "group": "[12,4]", "_id": {"$oid": "59515d813fce4a6697d4de09"}}, {"passport_label": "12.12-4.0.2-2-2-2-2-3-3.2", "gen_vectors": [[4, 5, 6, 1, 2, 3, 10, 11, 12, 7, 8, 9], [7, 9, 8, 10, 12, 11, 1, 3, 2, 4, 6, 5], [7, 9, 8, 10, 12, 11, 1, 3, 2, 4, 6, 5], [9, 8, 7, 12, 11, 10, 3, 2, 1, 6, 5, 4], [11, 10, 12, 8, 7, 9, 5, 4, 6, 2, 1, 3], [3, 1, 2, 6, 4, 5, 9, 7, 8, 12, 10, 11], [3, 1, 2, 6, 4, 5, 9, 7, 8, 12, 10, 11]], "total_label": "12.12-4.0.2-2-2-2-2-3-3.2.6", "cc": [2, 6], "label": "12.12-4.0.2-2-2-2-2-3-3", "genus": 12, "signature": "[0,2,2,2,2,2,3,3]", "group": "[12,4]", "_id": {"$oid": "59515d823fce4a6697d4de0a"}}, {"passport_label": "12.12-4.0.2-2-2-2-2-3-3.2", "gen_vectors": [[4, 5, 6, 1, 2, 3, 10, 11, 12, 7, 8, 9], [7, 9, 8, 10, 12, 11, 1, 3, 2, 4, 6, 5], [9, 8, 7, 12, 11, 10, 3, 2, 1, 6, 5, 4], [7, 9, 8, 10, 12, 11, 1, 3, 2, 4, 6, 5], [10, 12, 11, 7, 9, 8, 4, 6, 5, 1, 3, 2], [3, 1, 2, 6, 4, 5, 9, 7, 8, 12, 10, 11], [3, 1, 2, 6, 4, 5, 9, 7, 8, 12, 10, 11]], "total_label": "12.12-4.0.2-2-2-2-2-3-3.2.7", "cc": [2, 7], "label": "12.12-4.0.2-2-2-2-2-3-3", "genus": 12, "signature": "[0,2,2,2,2,2,3,3]", "group": "[12,4]", "_id": {"$oid": "59515d833fce4a6697d4de0b"}}, {"passport_label": "12.12-4.0.2-2-2-2-2-3-3.2", "gen_vectors": [[4, 5, 6, 1, 2, 3, 10, 11, 12, 7, 8, 9], [7, 9, 8, 10, 12, 11, 1, 3, 2, 4, 6, 5], [9, 8, 7, 12, 11, 10, 3, 2, 1, 6, 5, 4], [7, 9, 8, 10, 12, 11, 1, 3, 2, 4, 6, 5], [12, 11, 10, 9, 8, 7, 6, 5, 4, 3, 2, 1], [2, 3, 1, 5, 6, 4, 8, 9, 7, 11, 12, 10], [2, 3, 1, 5, 6, 4, 8, 9, 7, 11, 12, 10]], "total_label": "12.12-4.0.2-2-2-2-2-3-3.2.8", "cc": [2, 8], "label": "12.12-4.0.2-2-2-2-2-3-3", "genus": 12, "signature": "[0,2,2,2,2,2,3,3]", "group": "[12,4]", "_id": {"$oid": "59515d833fce4a6697d4de0c"}}, {"passport_label": "12.12-4.0.2-2-2-2-2-3-3.2", "gen_vectors": [[4, 5, 6, 1, 2, 3, 10, 11, 12, 7, 8, 9], [7, 9, 8, 10, 12, 11, 1, 3, 2, 4, 6, 5], [9, 8, 7, 12, 11, 10, 3, 2, 1, 6, 5, 4], [7, 9, 8, 10, 12, 11, 1, 3, 2, 4, 6, 5], [11, 10, 12, 8, 7, 9, 5, 4, 6, 2, 1, 3], [2, 3, 1, 5, 6, 4, 8, 9, 7, 11, 12, 10], [3, 1, 2, 6, 4, 5, 9, 7, 8, 12, 10, 11]], "total_label": "12.12-4.0.2-2-2-2-2-3-3.2.9", "cc": [2, 9], "label": "12.12-4.0.2-2-2-2-2-3-3", "genus": 12, "signature": "[0,2,2,2,2,2,3,3]", "group": "[12,4]", "_id": {"$oid": "59515d843fce4a6697d4de0d"}}, {"passport_label": "12.12-4.0.2-2-2-2-2-3-3.2", "gen_vectors": [[4, 5, 6, 1, 2, 3, 10, 11, 12, 7, 8, 9], [7, 9, 8, 10, 12, 11, 1, 3, 2, 4, 6, 5], [9, 8, 7, 12, 11, 10, 3, 2, 1, 6, 5, 4], [7, 9, 8, 10, 12, 11, 1, 3, 2, 4, 6, 5], [11, 10, 12, 8, 7, 9, 5, 4, 6, 2, 1, 3], [3, 1, 2, 6, 4, 5, 9, 7, 8, 12, 10, 11], [2, 3, 1, 5, 6, 4, 8, 9, 7, 11, 12, 10]], "total_label": "12.12-4.0.2-2-2-2-2-3-3.2.10", "cc": [2, 10], "label": "12.12-4.0.2-2-2-2-2-3-3", "genus": 12, "signature": "[0,2,2,2,2,2,3,3]", "group": "[12,4]", "_id": {"$oid": "59515d843fce4a6697d4de0e"}}, {"passport_label": "12.12-4.0.2-2-2-2-2-3-3.2", "gen_vectors": [[4, 5, 6, 1, 2, 3, 10, 11, 12, 7, 8, 9], [7, 9, 8, 10, 12, 11, 1, 3, 2, 4, 6, 5], [9, 8, 7, 12, 11, 10, 3, 2, 1, 6, 5, 4], [9, 8, 7, 12, 11, 10, 3, 2, 1, 6, 5, 4], [10, 12, 11, 7, 9, 8, 4, 6, 5, 1, 3, 2], [2, 3, 1, 5, 6, 4, 8, 9, 7, 11, 12, 10], [3, 1, 2, 6, 4, 5, 9, 7, 8, 12, 10, 11]], "total_label": "12.12-4.0.2-2-2-2-2-3-3.2.11", "cc": [2, 11], "label": "12.12-4.0.2-2-2-2-2-3-3", "genus": 12, "signature": "[0,2,2,2,2,2,3,3]", "group": "[12,4]", "_id": {"$oid": "59515d853fce4a6697d4de0f"}}, {"passport_label": "12.12-4.0.2-2-2-2-2-3-3.2", "gen_vectors": [[4, 5, 6, 1, 2, 3, 10, 11, 12, 7, 8, 9], [7, 9, 8, 10, 12, 11, 1, 3, 2, 4, 6, 5], [9, 8, 7, 12, 11, 10, 3, 2, 1, 6, 5, 4], [9, 8, 7, 12, 11, 10, 3, 2, 1, 6, 5, 4], [10, 12, 11, 7, 9, 8, 4, 6, 5, 1, 3, 2], [3, 1, 2, 6, 4, 5, 9, 7, 8, 12, 10, 11], [2, 3, 1, 5, 6, 4, 8, 9, 7, 11, 12, 10]], "total_label": "12.12-4.0.2-2-2-2-2-3-3.2.12", "cc": [2, 12], "label": "12.12-4.0.2-2-2-2-2-3-3", "genus": 12, "signature": "[0,2,2,2,2,2,3,3]", "group": "[12,4]", "_id": {"$oid": "59515d853fce4a6697d4de10"}}, {"passport_label": "12.12-4.0.2-2-2-2-2-3-3.2", "gen_vectors": [[4, 5, 6, 1, 2, 3, 10, 11, 12, 7, 8, 9], [7, 9, 8, 10, 12, 11, 1, 3, 2, 4, 6, 5], [9, 8, 7, 12, 11, 10, 3, 2, 1, 6, 5, 4], [9, 8, 7, 12, 11, 10, 3, 2, 1, 6, 5, 4], [12, 11, 10, 9, 8, 7, 6, 5, 4, 3, 2, 1], [3, 1, 2, 6, 4, 5, 9, 7, 8, 12, 10, 11], [3, 1, 2, 6, 4, 5, 9, 7, 8, 12, 10, 11]], "total_label": "12.12-4.0.2-2-2-2-2-3-3.2.13", "cc": [2, 13], "label": "12.12-4.0.2-2-2-2-2-3-3", "genus": 12, "signature": "[0,2,2,2,2,2,3,3]", "group": "[12,4]", "_id": {"$oid": "59515d863fce4a6697d4de11"}}, {"passport_label": "12.12-4.0.2-2-2-2-2-3-3.2", "gen_vectors": [[4, 5, 6, 1, 2, 3, 10, 11, 12, 7, 8, 9], [7, 9, 8, 10, 12, 11, 1, 3, 2, 4, 6, 5], [9, 8, 7, 12, 11, 10, 3, 2, 1, 6, 5, 4], [9, 8, 7, 12, 11, 10, 3, 2, 1, 6, 5, 4], [11, 10, 12, 8, 7, 9, 5, 4, 6, 2, 1, 3], [2, 3, 1, 5, 6, 4, 8, 9, 7, 11, 12, 10], [2, 3, 1, 5, 6, 4, 8, 9, 7, 11, 12, 10]], "total_label": "12.12-4.0.2-2-2-2-2-3-3.2.14", "cc": [2, 14], "label": "12.12-4.0.2-2-2-2-2-3-3", "genus": 12, "signature": "[0,2,2,2,2,2,3,3]", "group": "[12,4]", "_id": {"$oid": "59515d863fce4a6697d4de12"}}, {"passport_label": "12.12-4.0.2-2-2-2-2-3-3.2", "gen_vectors": [[4, 5, 6, 1, 2, 3, 10, 11, 12, 7, 8, 9], [7, 9, 8, 10, 12, 11, 1, 3, 2, 4, 6, 5], [9, 8, 7, 12, 11, 10, 3, 2, 1, 6, 5, 4], [8, 7, 9, 11, 10, 12, 2, 1, 3, 5, 4, 6], [10, 12, 11, 7, 9, 8, 4, 6, 5, 1, 3, 2], [2, 3, 1, 5, 6, 4, 8, 9, 7, 11, 12, 10], [2, 3, 1, 5, 6, 4, 8, 9, 7, 11, 12, 10]], "total_label": "12.12-4.0.2-2-2-2-2-3-3.2.15", "cc": [2, 15], "label": "12.12-4.0.2-2-2-2-2-3-3", "genus": 12, "signature": "[0,2,2,2,2,2,3,3]", "group": "[12,4]", "_id": {"$oid": "59515d873fce4a6697d4de13"}}, {"passport_label": "12.12-4.0.2-2-2-2-2-3-3.2", "gen_vectors": [[4, 5, 6, 1, 2, 3, 10, 11, 12, 7, 8, 9], [7, 9, 8, 10, 12, 11, 1, 3, 2, 4, 6, 5], [9, 8, 7, 12, 11, 10, 3, 2, 1, 6, 5, 4], [8, 7, 9, 11, 10, 12, 2, 1, 3, 5, 4, 6], [12, 11, 10, 9, 8, 7, 6, 5, 4, 3, 2, 1], [2, 3, 1, 5, 6, 4, 8, 9, 7, 11, 12, 10], [3, 1, 2, 6, 4, 5, 9, 7, 8, 12, 10, 11]], "total_label": "12.12-4.0.2-2-2-2-2-3-3.2.16", "cc": [2, 16], "label": "12.12-4.0.2-2-2-2-2-3-3", "genus": 12, "signature": "[0,2,2,2,2,2,3,3]", "group": "[12,4]", "_id": {"$oid": "59515d873fce4a6697d4de14"}}, {"passport_label": "12.12-4.0.2-2-2-2-2-3-3.2", "gen_vectors": [[4, 5, 6, 1, 2, 3, 10, 11, 12, 7, 8, 9], [7, 9, 8, 10, 12, 11, 1, 3, 2, 4, 6, 5], [9, 8, 7, 12, 11, 10, 3, 2, 1, 6, 5, 4], [8, 7, 9, 11, 10, 12, 2, 1, 3, 5, 4, 6], [12, 11, 10, 9, 8, 7, 6, 5, 4, 3, 2, 1], [3, 1, 2, 6, 4, 5, 9, 7, 8, 12, 10, 11], [2, 3, 1, 5, 6, 4, 8, 9, 7, 11, 12, 10]], "total_label": "12.12-4.0.2-2-2-2-2-3-3.2.17", "cc": [2, 17], "label": "12.12-4.0.2-2-2-2-2-3-3", "genus": 12, "signature": "[0,2,2,2,2,2,3,3]", "group": "[12,4]", "_id": {"$oid": "59515d883fce4a6697d4de15"}}, {"passport_label": "12.12-4.0.2-2-2-2-2-3-3.2", "gen_vectors": [[4, 5, 6, 1, 2, 3, 10, 11, 12, 7, 8, 9], [7, 9, 8, 10, 12, 11, 1, 3, 2, 4, 6, 5], [9, 8, 7, 12, 11, 10, 3, 2, 1, 6, 5, 4], [8, 7, 9, 11, 10, 12, 2, 1, 3, 5, 4, 6], [11, 10, 12, 8, 7, 9, 5, 4, 6, 2, 1, 3], [3, 1, 2, 6, 4, 5, 9, 7, 8, 12, 10, 11], [3, 1, 2, 6, 4, 5, 9, 7, 8, 12, 10, 11]], "total_label": "12.12-4.0.2-2-2-2-2-3-3.2.18", "cc": [2, 18], "label": "12.12-4.0.2-2-2-2-2-3-3", "genus": 12, "signature": "[0,2,2,2,2,2,3,3]", "group": "[12,4]", "_id": {"$oid": "59515d883fce4a6697d4de16"}}, {"passport_label": "12.12-4.0.2-2-2-2-2-3-3.3", "gen_vectors": [[4, 5, 6, 1, 2, 3, 10, 11, 12, 7, 8, 9], [7, 9, 8, 10, 12, 11, 1, 3, 2, 4, 6, 5], [10, 12, 11, 7, 9, 8, 4, 6, 5, 1, 3, 2], [10, 12, 11, 7, 9, 8, 4, 6, 5, 1, 3, 2], [10, 12, 11, 7, 9, 8, 4, 6, 5, 1, 3, 2], [2, 3, 1, 5, 6, 4, 8, 9, 7, 11, 12, 10], [3, 1, 2, 6, 4, 5, 9, 7, 8, 12, 10, 11]], "total_label": "12.12-4.0.2-2-2-2-2-3-3.3.1", "cc": [3, 1], "label": "12.12-4.0.2-2-2-2-2-3-3", "genus": 12, "signature": "[0,2,2,2,2,2,3,3]", "group": "[12,4]", "_id": {"$oid": "59515d893fce4a6697d4de17"}}, {"passport_label": "12.12-4.0.2-2-2-2-2-3-3.3", "gen_vectors": [[4, 5, 6, 1, 2, 3, 10, 11, 12, 7, 8, 9], [7, 9, 8, 10, 12, 11, 1, 3, 2, 4, 6, 5], [10, 12, 11, 7, 9, 8, 4, 6, 5, 1, 3, 2], [10, 12, 11, 7, 9, 8, 4, 6, 5, 1, 3, 2], [12, 11, 10, 9, 8, 7, 6, 5, 4, 3, 2, 1], [3, 1, 2, 6, 4, 5, 9, 7, 8, 12, 10, 11], [3, 1, 2, 6, 4, 5, 9, 7, 8, 12, 10, 11]], "total_label": "12.12-4.0.2-2-2-2-2-3-3.3.2", "cc": [3, 2], "label": "12.12-4.0.2-2-2-2-2-3-3", "genus": 12, "signature": "[0,2,2,2,2,2,3,3]", "group": "[12,4]", "_id": {"$oid": "59515d8a3fce4a6697d4de18"}}, {"passport_label": "12.12-4.0.2-2-2-2-2-3-3.3", "gen_vectors": [[4, 5, 6, 1, 2, 3, 10, 11, 12, 7, 8, 9], [7, 9, 8, 10, 12, 11, 1, 3, 2, 4, 6, 5], [10, 12, 11, 7, 9, 8, 4, 6, 5, 1, 3, 2], [12, 11, 10, 9, 8, 7, 6, 5, 4, 3, 2, 1], [10, 12, 11, 7, 9, 8, 4, 6, 5, 1, 3, 2], [2, 3, 1, 5, 6, 4, 8, 9, 7, 11, 12, 10], [2, 3, 1, 5, 6, 4, 8, 9, 7, 11, 12, 10]], "total_label": "12.12-4.0.2-2-2-2-2-3-3.3.3", "cc": [3, 3], "label": "12.12-4.0.2-2-2-2-2-3-3", "genus": 12, "signature": "[0,2,2,2,2,2,3,3]", "group": "[12,4]", "_id": {"$oid": "59515d8a3fce4a6697d4de19"}}, {"passport_label": "12.12-4.0.2-2-2-2-2-3-3.3", "gen_vectors": [[4, 5, 6, 1, 2, 3, 10, 11, 12, 7, 8, 9], [7, 9, 8, 10, 12, 11, 1, 3, 2, 4, 6, 5], [10, 12, 11, 7, 9, 8, 4, 6, 5, 1, 3, 2], [12, 11, 10, 9, 8, 7, 6, 5, 4, 3, 2, 1], [12, 11, 10, 9, 8, 7, 6, 5, 4, 3, 2, 1], [2, 3, 1, 5, 6, 4, 8, 9, 7, 11, 12, 10], [3, 1, 2, 6, 4, 5, 9, 7, 8, 12, 10, 11]], "total_label": "12.12-4.0.2-2-2-2-2-3-3.3.4", "cc": [3, 4], "label": "12.12-4.0.2-2-2-2-2-3-3", "genus": 12, "signature": "[0,2,2,2,2,2,3,3]", "group": "[12,4]", "_id": {"$oid": "59515d8a3fce4a6697d4de1a"}}, {"passport_label": "12.12-4.0.2-2-2-2-2-3-3.3", "gen_vectors": [[4, 5, 6, 1, 2, 3, 10, 11, 12, 7, 8, 9], [7, 9, 8, 10, 12, 11, 1, 3, 2, 4, 6, 5], [10, 12, 11, 7, 9, 8, 4, 6, 5, 1, 3, 2], [12, 11, 10, 9, 8, 7, 6, 5, 4, 3, 2, 1], [12, 11, 10, 9, 8, 7, 6, 5, 4, 3, 2, 1], [3, 1, 2, 6, 4, 5, 9, 7, 8, 12, 10, 11], [2, 3, 1, 5, 6, 4, 8, 9, 7, 11, 12, 10]], "total_label": "12.12-4.0.2-2-2-2-2-3-3.3.5", "cc": [3, 5], "label": "12.12-4.0.2-2-2-2-2-3-3", "genus": 12, "signature": "[0,2,2,2,2,2,3,3]", "group": "[12,4]", "_id": {"$oid": "59515d8b3fce4a6697d4de1b"}}, {"passport_label": "12.12-4.0.2-2-2-2-2-3-3.3", "gen_vectors": [[4, 5, 6, 1, 2, 3, 10, 11, 12, 7, 8, 9], [7, 9, 8, 10, 12, 11, 1, 3, 2, 4, 6, 5], [10, 12, 11, 7, 9, 8, 4, 6, 5, 1, 3, 2], [12, 11, 10, 9, 8, 7, 6, 5, 4, 3, 2, 1], [11, 10, 12, 8, 7, 9, 5, 4, 6, 2, 1, 3], [3, 1, 2, 6, 4, 5, 9, 7, 8, 12, 10, 11], [3, 1, 2, 6, 4, 5, 9, 7, 8, 12, 10, 11]], "total_label": "12.12-4.0.2-2-2-2-2-3-3.3.6", "cc": [3, 6], "label": "12.12-4.0.2-2-2-2-2-3-3", "genus": 12, "signature": "[0,2,2,2,2,2,3,3]", "group": "[12,4]", "_id": {"$oid": "59515d8c3fce4a6697d4de1c"}}, {"passport_label": "12.12-4.0.2-2-2-2-2-3-3.3", "gen_vectors": [[4, 5, 6, 1, 2, 3, 10, 11, 12, 7, 8, 9], [7, 9, 8, 10, 12, 11, 1, 3, 2, 4, 6, 5], [12, 11, 10, 9, 8, 7, 6, 5, 4, 3, 2, 1], [10, 12, 11, 7, 9, 8, 4, 6, 5, 1, 3, 2], [10, 12, 11, 7, 9, 8, 4, 6, 5, 1, 3, 2], [3, 1, 2, 6, 4, 5, 9, 7, 8, 12, 10, 11], [3, 1, 2, 6, 4, 5, 9, 7, 8, 12, 10, 11]], "total_label": "12.12-4.0.2-2-2-2-2-3-3.3.7", "cc": [3, 7], "label": "12.12-4.0.2-2-2-2-2-3-3", "genus": 12, "signature": "[0,2,2,2,2,2,3,3]", "group": "[12,4]", "_id": {"$oid": "59515d8c3fce4a6697d4de1d"}}, {"passport_label": "12.12-4.0.2-2-2-2-2-3-3.3", "gen_vectors": [[4, 5, 6, 1, 2, 3, 10, 11, 12, 7, 8, 9], [7, 9, 8, 10, 12, 11, 1, 3, 2, 4, 6, 5], [12, 11, 10, 9, 8, 7, 6, 5, 4, 3, 2, 1], [10, 12, 11, 7, 9, 8, 4, 6, 5, 1, 3, 2], [12, 11, 10, 9, 8, 7, 6, 5, 4, 3, 2, 1], [2, 3, 1, 5, 6, 4, 8, 9, 7, 11, 12, 10], [2, 3, 1, 5, 6, 4, 8, 9, 7, 11, 12, 10]], "total_label": "12.12-4.0.2-2-2-2-2-3-3.3.8", "cc": [3, 8], "label": "12.12-4.0.2-2-2-2-2-3-3", "genus": 12, "signature": "[0,2,2,2,2,2,3,3]", "group": "[12,4]", "_id": {"$oid": "59515d8d3fce4a6697d4de1e"}}, {"passport_label": "12.12-4.0.2-2-2-2-2-3-3.3", "gen_vectors": [[4, 5, 6, 1, 2, 3, 10, 11, 12, 7, 8, 9], [7, 9, 8, 10, 12, 11, 1, 3, 2, 4, 6, 5], [12, 11, 10, 9, 8, 7, 6, 5, 4, 3, 2, 1], [10, 12, 11, 7, 9, 8, 4, 6, 5, 1, 3, 2], [11, 10, 12, 8, 7, 9, 5, 4, 6, 2, 1, 3], [2, 3, 1, 5, 6, 4, 8, 9, 7, 11, 12, 10], [3, 1, 2, 6, 4, 5, 9, 7, 8, 12, 10, 11]], "total_label": "12.12-4.0.2-2-2-2-2-3-3.3.9", "cc": [3, 9], "label": "12.12-4.0.2-2-2-2-2-3-3", "genus": 12, "signature": "[0,2,2,2,2,2,3,3]", "group": "[12,4]", "_id": {"$oid": "59515d8e3fce4a6697d4de1f"}}, {"passport_label": "12.12-4.0.2-2-2-2-2-3-3.3", "gen_vectors": [[4, 5, 6, 1, 2, 3, 10, 11, 12, 7, 8, 9], [7, 9, 8, 10, 12, 11, 1, 3, 2, 4, 6, 5], [12, 11, 10, 9, 8, 7, 6, 5, 4, 3, 2, 1], [10, 12, 11, 7, 9, 8, 4, 6, 5, 1, 3, 2], [11, 10, 12, 8, 7, 9, 5, 4, 6, 2, 1, 3], [3, 1, 2, 6, 4, 5, 9, 7, 8, 12, 10, 11], [2, 3, 1, 5, 6, 4, 8, 9, 7, 11, 12, 10]], "total_label": "12.12-4.0.2-2-2-2-2-3-3.3.10", "cc": [3, 10], "label": "12.12-4.0.2-2-2-2-2-3-3", "genus": 12, "signature": "[0,2,2,2,2,2,3,3]", "group": "[12,4]", "_id": {"$oid": "59515d8e3fce4a6697d4de20"}}, {"passport_label": "12.12-4.0.2-2-2-2-2-3-3.3", "gen_vectors": [[4, 5, 6, 1, 2, 3, 10, 11, 12, 7, 8, 9], [7, 9, 8, 10, 12, 11, 1, 3, 2, 4, 6, 5], [12, 11, 10, 9, 8, 7, 6, 5, 4, 3, 2, 1], [12, 11, 10, 9, 8, 7, 6, 5, 4, 3, 2, 1], [10, 12, 11, 7, 9, 8, 4, 6, 5, 1, 3, 2], [2, 3, 1, 5, 6, 4, 8, 9, 7, 11, 12, 10], [3, 1, 2, 6, 4, 5, 9, 7, 8, 12, 10, 11]], "total_label": "12.12-4.0.2-2-2-2-2-3-3.3.11", "cc": [3, 11], "label": "12.12-4.0.2-2-2-2-2-3-3", "genus": 12, "signature": "[0,2,2,2,2,2,3,3]", "group": "[12,4]", "_id": {"$oid": "59515d8f3fce4a6697d4de21"}}, {"passport_label": "12.12-4.0.2-2-2-2-2-3-3.3", "gen_vectors": [[4, 5, 6, 1, 2, 3, 10, 11, 12, 7, 8, 9], [7, 9, 8, 10, 12, 11, 1, 3, 2, 4, 6, 5], [12, 11, 10, 9, 8, 7, 6, 5, 4, 3, 2, 1], [12, 11, 10, 9, 8, 7, 6, 5, 4, 3, 2, 1], [10, 12, 11, 7, 9, 8, 4, 6, 5, 1, 3, 2], [3, 1, 2, 6, 4, 5, 9, 7, 8, 12, 10, 11], [2, 3, 1, 5, 6, 4, 8, 9, 7, 11, 12, 10]], "total_label": "12.12-4.0.2-2-2-2-2-3-3.3.12", "cc": [3, 12], "label": "12.12-4.0.2-2-2-2-2-3-3", "genus": 12, "signature": "[0,2,2,2,2,2,3,3]", "group": "[12,4]", "_id": {"$oid": "59515d8f3fce4a6697d4de22"}}, {"passport_label": "12.12-4.0.2-2-2-2-2-3-3.3", "gen_vectors": [[4, 5, 6, 1, 2, 3, 10, 11, 12, 7, 8, 9], [7, 9, 8, 10, 12, 11, 1, 3, 2, 4, 6, 5], [12, 11, 10, 9, 8, 7, 6, 5, 4, 3, 2, 1], [12, 11, 10, 9, 8, 7, 6, 5, 4, 3, 2, 1], [12, 11, 10, 9, 8, 7, 6, 5, 4, 3, 2, 1], [3, 1, 2, 6, 4, 5, 9, 7, 8, 12, 10, 11], [3, 1, 2, 6, 4, 5, 9, 7, 8, 12, 10, 11]], "total_label": "12.12-4.0.2-2-2-2-2-3-3.3.13", "cc": [3, 13], "label": "12.12-4.0.2-2-2-2-2-3-3", "genus": 12, "signature": "[0,2,2,2,2,2,3,3]", "group": "[12,4]", "_id": {"$oid": "59515d8f3fce4a6697d4de23"}}, {"passport_label": "12.12-4.0.2-2-2-2-2-3-3.3", "gen_vectors": [[4, 5, 6, 1, 2, 3, 10, 11, 12, 7, 8, 9], [7, 9, 8, 10, 12, 11, 1, 3, 2, 4, 6, 5], [12, 11, 10, 9, 8, 7, 6, 5, 4, 3, 2, 1], [12, 11, 10, 9, 8, 7, 6, 5, 4, 3, 2, 1], [11, 10, 12, 8, 7, 9, 5, 4, 6, 2, 1, 3], [2, 3, 1, 5, 6, 4, 8, 9, 7, 11, 12, 10], [2, 3, 1, 5, 6, 4, 8, 9, 7, 11, 12, 10]], "total_label": "12.12-4.0.2-2-2-2-2-3-3.3.14", "cc": [3, 14], "label": "12.12-4.0.2-2-2-2-2-3-3", "genus": 12, "signature": "[0,2,2,2,2,2,3,3]", "group": "[12,4]", "_id": {"$oid": "59515d903fce4a6697d4de24"}}, {"passport_label": "12.12-4.0.2-2-2-2-2-3-3.3", "gen_vectors": [[4, 5, 6, 1, 2, 3, 10, 11, 12, 7, 8, 9], [7, 9, 8, 10, 12, 11, 1, 3, 2, 4, 6, 5], [12, 11, 10, 9, 8, 7, 6, 5, 4, 3, 2, 1], [11, 10, 12, 8, 7, 9, 5, 4, 6, 2, 1, 3], [10, 12, 11, 7, 9, 8, 4, 6, 5, 1, 3, 2], [2, 3, 1, 5, 6, 4, 8, 9, 7, 11, 12, 10], [2, 3, 1, 5, 6, 4, 8, 9, 7, 11, 12, 10]], "total_label": "12.12-4.0.2-2-2-2-2-3-3.3.15", "cc": [3, 15], "label": "12.12-4.0.2-2-2-2-2-3-3", "genus": 12, "signature": "[0,2,2,2,2,2,3,3]", "group": "[12,4]", "_id": {"$oid": "59515d903fce4a6697d4de25"}}, {"passport_label": "12.12-4.0.2-2-2-2-2-3-3.3", "gen_vectors": [[4, 5, 6, 1, 2, 3, 10, 11, 12, 7, 8, 9], [7, 9, 8, 10, 12, 11, 1, 3, 2, 4, 6, 5], [12, 11, 10, 9, 8, 7, 6, 5, 4, 3, 2, 1], [11, 10, 12, 8, 7, 9, 5, 4, 6, 2, 1, 3], [12, 11, 10, 9, 8, 7, 6, 5, 4, 3, 2, 1], [2, 3, 1, 5, 6, 4, 8, 9, 7, 11, 12, 10], [3, 1, 2, 6, 4, 5, 9, 7, 8, 12, 10, 11]], "total_label": "12.12-4.0.2-2-2-2-2-3-3.3.16", "cc": [3, 16], "label": "12.12-4.0.2-2-2-2-2-3-3", "genus": 12, "signature": "[0,2,2,2,2,2,3,3]", "group": "[12,4]", "_id": {"$oid": "59515d913fce4a6697d4de26"}}, {"passport_label": "12.12-4.0.2-2-2-2-2-3-3.3", "gen_vectors": [[4, 5, 6, 1, 2, 3, 10, 11, 12, 7, 8, 9], [7, 9, 8, 10, 12, 11, 1, 3, 2, 4, 6, 5], [12, 11, 10, 9, 8, 7, 6, 5, 4, 3, 2, 1], [11, 10, 12, 8, 7, 9, 5, 4, 6, 2, 1, 3], [12, 11, 10, 9, 8, 7, 6, 5, 4, 3, 2, 1], [3, 1, 2, 6, 4, 5, 9, 7, 8, 12, 10, 11], [2, 3, 1, 5, 6, 4, 8, 9, 7, 11, 12, 10]], "total_label": "12.12-4.0.2-2-2-2-2-3-3.3.17", "cc": [3, 17], "label": "12.12-4.0.2-2-2-2-2-3-3", "genus": 12, "signature": "[0,2,2,2,2,2,3,3]", "group": "[12,4]", "_id": {"$oid": "59515d923fce4a6697d4de27"}}, {"passport_label": "12.12-4.0.2-2-2-2-2-3-3.3", "gen_vectors": [[4, 5, 6, 1, 2, 3, 10, 11, 12, 7, 8, 9], [7, 9, 8, 10, 12, 11, 1, 3, 2, 4, 6, 5], [12, 11, 10, 9, 8, 7, 6, 5, 4, 3, 2, 1], [11, 10, 12, 8, 7, 9, 5, 4, 6, 2, 1, 3], [11, 10, 12, 8, 7, 9, 5, 4, 6, 2, 1, 3], [3, 1, 2, 6, 4, 5, 9, 7, 8, 12, 10, 11], [3, 1, 2, 6, 4, 5, 9, 7, 8, 12, 10, 11]], "total_label": "12.12-4.0.2-2-2-2-2-3-3.3.18", "cc": [3, 18], "label": "12.12-4.0.2-2-2-2-2-3-3", "genus": 12, "signature": "[0,2,2,2,2,2,3,3]", "group": "[12,4]", "_id": {"$oid": "59515d923fce4a6697d4de28"}}]
